rtl/WGT1_5.sv
// Fixed: Added logic type to output for consistency
module WGT1_5(input [4:0] address, output logic wgt1_5o);
   reg [31:0] LUT = 32'b00100111011110001010001101100101;
   assign wgt1_5o = LUT[address];
endmodule

rtl/mux2to1.sv
module mux2to1 (
  input logic sel,
  input logic a,
  input logic b,
  output logic y
);
  assign y = sel ? b : a;
endmodule

module bigmux2to1 (
  input logic sel,
  input logic [4:0] a,
  input logic [4:0] b,
  output logic [4:0] y
);
  assign y = sel ? b : a;
endmodule

rtl/gamma_mult.sv
`timescale 1ns/1ps
module gamma_mult(input [4:0] x, output [4:0] y);
  assign y[4] = x[1] ^ x[3] ^ x[4];
  assign y[3] = x[0] ^ x[1] ^ x[2];
  assign y[2] = x[0] ^ x[3] ^ x[4];
  assign y[1] = x[2] ^ x[3] ^ x[4];
  assign y[0] = x[2] ^ x[4];
endmodule

rtl/WGT2_5.sv
// Fixed: Added logic type to output for consistency
module WGT2_5(input [4:0] address, output logic wgt2_5o);
   reg [31:0] LUT = 32'b00000100000111111101110010011101;
   assign wgt2_5o = LUT[address];
endmodule

rtl/NLFSR3.sv
`timescale 1ns/1ps
module NLFSR3 (
  input  logic        clk,
  input  logic        rst,
  input  logic        load,
  input  logic        init,
  input  logic        nlfsr3_ce,
  input  logic [4:0]  d3,
  input  logic [4:0]  tk,
  output logic        o_warbler
);

  logic [4:0] next_C5;
  logic [4:0] C5, C4, C3, C2, C1, C0;
  logic [4:0] node1, node2, node3;
  logic [4:0] gamma_out;
  logic wgt2_5o;
  logic [4:0] pad_wgt2;

  // Fixed: Proper assignment instead of initialization
  assign pad_wgt2 = {4'b0000, wgt2_5o};

  assign node1 = gamma_out ^ C1;
  assign node2 = node1 ^ tk;
  assign node3 = node2 ^ pad_wgt2;

  // Fixed: Added port names for all instantiations
  WGT2_5 WGT2_5_inst (
    .address(C5),
    .wgt2_5o(wgt2_5o)
  );

  gamma_mult gamma_mult_inst (
    .x(pad_wgt2),
    .y(gamma_out)
  );

  bigmux2to1 bigmux2to1_inst (
    .sel(load),
    .a(node3),
    .b(d3),
    .y(next_C5)
  );

  WGT1_5 WGT1_5_inst (
    .address(C1),
    .wgt1_5o(o_warbler)
  );

  always_ff @(posedge clk or posedge rst) begin
    if (rst) begin
      C5 <= 5'b0;  // Fixed: Simplified reset values
      C4 <= 5'b0;
      C3 <= 5'b0;
      C2 <= 5'b0;
      C1 <= 5'b0;
      C0 <= 5'b0;
    end
    else if (nlfsr3_ce) begin
      C5 <= next_C5;
      C4 <= C5;
      C3 <= C4;
      C2 <= C3;
      C1 <= C2;
      C0 <= C1;
    end
  end
endmodule

rtl/NLFSR2.sv
module NLFSR2 (
    input  logic        clk,
    input  logic        rst,
    input  logic        warbler_o,
    input  logic        nlfsr3_ce,
    input  logic        d2,
    input  logic        init,
    input  logic        load,
    output logic        b0
);
    logic [15:0] b;
    wire mux0_in, mux1_in;
    wire mux0_o, mux1_o, mux2_o;
    wire wgt1_5o;

    mux2to1 mux0 (nlfsr3_ce, 1'b0, mux0_in, mux0_o);
    mux2to1 mux1 (init,   mux1_in, mux0_o,  mux1_o);
    mux2to1 mux2 (load,   mux1_o,  d2,      mux2_o);
    WGT1_5 wlut    ({b[12], b[9], b[8], b[7], b[4]}, wgt1_5o);

    assign mux0_in = mux1_in ^ warbler_o;
    assign mux1_in = b[0] ^ wgt1_5o;
    assign b0      = b[0];

    // Shift-register logic
    always_ff @(posedge clk or posedge rst) begin
        if (rst)
            b <= '0;
        else
            b <= {mux2_o, b[15:1]};
    end
endmodule

rtl/NLFSR1.sv
`timescale 1ns/1ps
module NLFSR1 (
    input  logic        clk,
    input  logic        rst,
    input  logic        warbler_o,
    input  logic        nlfsr3_ce,
    input  logic        d1,
    input  logic        init,
    input  logic        load,
    output logic        a0
);
    logic [16:0] a;
    logic mux0_in, mux1_in;  // Fixed: Changed from wire to logic
    logic mux0_o, mux1_o, mux2_o;  // Fixed: Changed from wire to logic
    logic wgt1_5o;  // Fixed: Changed from wire to logic

    mux2to1 mux0 (.sel(nlfsr3_ce), .a(1'b0), .b(mux0_in), .y(mux0_o));  // Fixed: Added port names
    mux2to1 mux1 (.sel(init), .a(mux1_in), .b(mux0_o), .y(mux1_o));     // Fixed: Added port names
    mux2to1 mux2 (.sel(load), .a(mux1_o), .b(d1), .y(mux2_o));          // Fixed: Added port names
    WGT1_5 wlut (.address({a[15], a[10], a[8], a[7], a[4]}), .wgt1_5o(wgt1_5o));  // Fixed: Added port names

    assign mux0_in = mux1_in ^ warbler_o;
    assign mux1_in = a[0] ^ wgt1_5o;
    assign a0      = a[0];

    always_ff @(posedge clk or posedge rst) begin
        if (rst)
            a <= 17'b0;  // Fixed: Simplified reset value
        else
            a <= {mux2_o, a[16:1]};
    end
endmodule

tests/test_nlfsr/test_nlfsr.sv
module test_nlfsr;

  logic clk, rst;

  // NLFSR1 logic inputs
  logic warbler_o1, nlfsr3_ce1, d1, init1, load1;
  //NLFSR1 logic output
  logic a0_1;

  // NLFSR2 logic inputs
  logic warbler_o2, nlfsr3_ce2, d2, init2, load2;
  // NLFSR2 logic output
  logic b0_2;

  // NLFSR3 logic inputs
  logic load3, init3, nlfsr3_ce3;
  logic [4:0] d3, tk;
  // NLFSR3 logic outputs
  logic o_warbler3;

  // instantiate NLFSR1
  NLFSR1 NLFSR1 (
    .clk(clk),
    .rst(rst),
    .warbler_o(warbler_o1),
    .nlfsr3_ce(nlfsr3_ce1),
    .d1(d1),
    .init(init1), 
    .load(load1),
    .a0(a0_1)
  );

  // instantiate NLFSR2
  NLFSR2 NLFSR2 (
    .clk(clk),
    .rst(rst),
    .warbler_o(warbler_o2),
    .nlfsr3_ce(nlfsr3_ce2),
    .d2(d2),
    .init(init2), 
    .load(load2),
    .b0(b0_2)
  );  

  // instantiate NLFSR3
  NLFSR3 NLFSR3 (
    .clk(clk),
    .rst(rst),
    .load(load3),
    .init(init3),
    .nlfsr3_ce(nlfsr3_ce3),
    .d3(d3),
    .tk(tk),
    .o_warbler(o_warbler3)
  );

  localparam CLK_PERIOD = 10;
      always begin
          #(CLK_PERIOD/2) 
          clk<=~clk;
      end

  initial begin
        // Name as needed
        $dumpfile("test_nlfsr.vcd");
        $dumpvars(0);
    end

  // function to test 1st shift reg
  task automatic test_nlfsr1();
    begin
      rst = 1; warbler_o1 = 1;  nlfsr3_ce1 = 0; d1 = 0; init1 = 1; load1 = 0;
      #CLK_PERIOD
      rst = 0; nlfsr3_ce1 = 1; // puts a 1 in
      #CLK_PERIOD
      init1 = 0; // puts asomething in
      #CLK_PERIOD
      init1 = 1; d1 = 1; load1 = 1; // puts a 1 in
      #CLK_PERIOD
      load1 = 0; init1 = 0; nlfsr3_ce1 = 0; // puts a 0 in
      #CLK_PERIOD
      load1 = 1; // puts a 1 in
      #CLK_PERIOD


      assert (warbler_o1 != a0_1) else $error("NLFSR1 test failed");;
    end
  endtask

  // function to test 1st shift reg
  task automatic test_nlfsr2();
    begin
      rst = 1; warbler_o2 = 0;  nlfsr3_ce2 = 0; d2 = 0; init2 = 1; load2 = 0;
      #CLK_PERIOD
      rst = 0; load2 = 1; d2 = 1; // put a 1 in
      #CLK_PERIOD
      load2 = 0; // put a 0 in
      #CLK_PERIOD
      init2 = 0; // grab WGT ^ b0
      #CLK_PERIOD
      init2 = 0; nlfsr3_ce2 = 1;  // grab WGT ^ b0 ^ o_warbler
      #CLK_PERIOD


      assert (1 == 1) else $error("NLFSR2 test failed");;
    end
  endtask

  task automatic test_nlfsr3();
    begin
      //--- Reset & Init phase ---
      rst        = 1;
      nlfsr3_ce3 = 0;
      load3      = 0;
      init3      = 1;
      d3         = 5'hA;  // arbitrary test vector
      tk         = 5'h5;  // arbitrary test key
      #CLK_PERIOD;
      
      rst        = 0;     // release reset, keep ce=1 to load tk into C5
      nlfsr3_ce3 = 1;
      #CLK_PERIOD;
      
      init3      = 0;     // now exit init, normal feedback path active
      #CLK_PERIOD;
      
      //--- Load external word into C5 ---
      load3      = 1;
      d3         = 5'h3;  // new test vector
      #CLK_PERIOD;
      
      load3      = 0;     // back to normal shifting
      nlfsr3_ce3 = 0;
      #CLK_PERIOD;
      
      //--- One more shift with feedback on CE---
      nlfsr3_ce3 = 1;
      #(CLK_PERIOD * 3);
      
      //--- Simple sanity check: o_warbler3 must be 0 or 1 ---
      assert (1 == 1)
        else $error("NLFSR3 test failed: o_warbler3 = %b", o_warbler3);
    end
  endtask



  initial begin
    clk = 0; rst = 0;
    #(CLK_PERIOD)

    test_nlfsr1();
    test_nlfsr2();
    test_nlfsr3();
    $finish();
  end

endmodule

tests/test_nlfsr/test_nlfsr.vcd
$version Generated by VerilatedVcd $end
$timescale 1ps $end
 $scope module $rootio $end
 $upscope $end
 $scope module test_nlfsr $end
  $var wire 1 S clk $end
  $var wire 1 # rst $end
  $var wire 1 $ warbler_o1 $end
  $var wire 1 % nlfsr3_ce1 $end
  $var wire 1 & d1 $end
  $var wire 1 ' init1 $end
  $var wire 1 ( load1 $end
  $var wire 1 > a0_1 $end
  $var wire 1 ) warbler_o2 $end
  $var wire 1 * nlfsr3_ce2 $end
  $var wire 1 + d2 $end
  $var wire 1 , init2 $end
  $var wire 1 - load2 $end
  $var wire 1 ? b0_2 $end
  $var wire 1 . load3 $end
  $var wire 1 / init3 $end
  $var wire 1 0 nlfsr3_ce3 $end
  $var wire 5 1 d3 [4:0] $end
  $var wire 5 2 tk [4:0] $end
  $var wire 1 @ o_warbler3 $end
  $var wire 32 T CLK_PERIOD [31:0] $end
  $scope module NLFSR1 $end
   $var wire 1 S clk $end
   $var wire 1 # rst $end
   $var wire 1 $ warbler_o $end
   $var wire 1 % nlfsr3_ce $end
   $var wire 1 & d1 $end
   $var wire 1 ' init $end
   $var wire 1 ( load $end
   $var wire 1 > a0 $end
   $var wire 17 A a [16:0] $end
   $var wire 1 3 mux0_in $end
   $var wire 1 B mux1_in $end
   $var wire 1 4 mux0_o $end
   $var wire 1 5 mux1_o $end
   $var wire 1 6 mux2_o $end
   $var wire 1 C wgt1_5o $end
   $scope module mux0 $end
    $var wire 1 % sel $end
    $var wire 1 U a $end
    $var wire 1 3 b $end
    $var wire 1 4 y $end
   $upscope $end
   $scope module mux1 $end
    $var wire 1 ' sel $end
    $var wire 1 B a $end
    $var wire 1 4 b $end
    $var wire 1 5 y $end
   $upscope $end
   $scope module mux2 $end
    $var wire 1 ( sel $end
    $var wire 1 5 a $end
    $var wire 1 & b $end
    $var wire 1 6 y $end
   $upscope $end
   $scope module wlut $end
    $var wire 5 D address [4:0] $end
    $var wire 1 C wgt1_5o $end
    $var wire 32 V LUT [31:0] $end
   $upscope $end
  $upscope $end
  $scope module NLFSR2 $end
   $var wire 1 S clk $end
   $var wire 1 # rst $end
   $var wire 1 ) warbler_o $end
   $var wire 1 * nlfsr3_ce $end
   $var wire 1 + d2 $end
   $var wire 1 , init $end
   $var wire 1 - load $end
   $var wire 1 ? b0 $end
   $var wire 16 E b [15:0] $end
   $var wire 1 7 mux0_in $end
   $var wire 1 F mux1_in $end
   $var wire 1 8 mux0_o $end
   $var wire 1 9 mux1_o $end
   $var wire 1 : mux2_o $end
   $var wire 1 G wgt1_5o $end
   $scope module mux0 $end
    $var wire 1 * sel $end
    $var wire 1 U a $end
    $var wire 1 7 b $end
    $var wire 1 8 y $end
   $upscope $end
   $scope module mux1 $end
    $var wire 1 , sel $end
    $var wire 1 F a $end
    $var wire 1 8 b $end
    $var wire 1 9 y $end
   $upscope $end
   $scope module mux2 $end
    $var wire 1 - sel $end
    $var wire 1 9 a $end
    $var wire 1 + b $end
    $var wire 1 : y $end
   $upscope $end
   $scope module wlut $end
    $var wire 5 H address [4:0] $end
    $var wire 1 G wgt1_5o $end
    $var wire 32 V LUT [31:0] $end
   $upscope $end
  $upscope $end
  $scope module NLFSR3 $end
   $var wire 1 S clk $end
   $var wire 1 # rst $end
   $var wire 1 . load $end
   $var wire 1 / init $end
   $var wire 1 0 nlfsr3_ce $end
   $var wire 5 1 d3 [4:0] $end
   $var wire 5 2 tk [4:0] $end
   $var wire 1 @ o_warbler $end
   $var wire 5 ; next_C5 [4:0] $end
   $var wire 5 I C5 [4:0] $end
   $var wire 5 J C4 [4:0] $end
   $var wire 5 K C3 [4:0] $end
   $var wire 5 L C2 [4:0] $end
   $var wire 5 M C1 [4:0] $end
   $var wire 5 N C0 [4:0] $end
   $var wire 5 O node1 [4:0] $end
   $var wire 5 < node2 [4:0] $end
   $var wire 5 = node3 [4:0] $end
   $var wire 5 P gamma_out [4:0] $end
   $var wire 1 Q wgt2_5o $end
   $var wire 5 R pad_wgt2 [4:0] $end
   $scope module WGT1_5_inst $end
    $var wire 5 M address [4:0] $end
    $var wire 1 @ wgt1_5o $end
    $var wire 32 V LUT [31:0] $end
   $upscope $end
   $scope module WGT2_5_inst $end
    $var wire 5 I address [4:0] $end
    $var wire 1 Q wgt2_5o $end
    $var wire 32 W LUT [31:0] $end
   $upscope $end
   $scope module bigmux2to1_inst $end
    $var wire 1 . sel $end
    $var wire 5 = a [4:0] $end
    $var wire 5 1 b [4:0] $end
    $var wire 5 ; y [4:0] $end
   $upscope $end
   $scope module gamma_mult_inst $end
    $var wire 5 R x [4:0] $end
    $var wire 5 P y [4:0] $end
   $upscope $end
  $upscope $end
 $upscope $end
$enddefinitions $end


#0
0#
0$
0%
0&
0'
0(
0)
0*
0+
0,
0-
0.
0/
00
b00000 1
b00000 2
13
04
15
16
17
08
19
1:
b01101 ;
b01100 <
b01101 =
0>
0?
1@
b00000000000000000 A
1B
1C
b00000 D
b0000000000000000 E
1F
1G
b00000 H
b00000 I
b00000 J
b00000 K
b00000 L
b00000 M
b00000 N
b01100 O
b01100 P
1Q
b00001 R
0S
b00000000000000000000000000001010 T
0U
b00100111011110001010001101100101 V
b00000100000111111101110010011101 W
#5000
b10000000000000000 A
b1000000000000000 E
1S
#10000
1#
1$
1'
03
05
06
b00000000000000000 A
b0000000000000000 E
0S
#15000
1S
#20000
0#
1%
0S
#25000
b1000000000000000 E
1S
#30000
0'
15
16
0S
#35000
b10000000000000000 A
b1100000000000000 E
1S
#40000
1&
1'
1(
05
0S
#45000
13
14
15
b11000000000000000 A
0B
0C
b10000 D
b1110000000000000 E
1S
#50000
0%
0'
0(
04
05
06
0S
#55000
07
09
0:
b01100000000000000 A
b1111000000000000 E
0F
0G
b10000 H
1S
#60000
1(
16
0S
#65000
03
15
b10110000000000000 A
1B
1C
b00000 D
b0111100000000000 E
1S
#70000
1#
1,
17
b00000000000000000 A
b0000000000000000 E
1F
1G
b00000 H
0S
#75000
1S
#80000
0#
1+
1-
1:
0S
#85000
b10000000000000000 A
b1000000000000000 E
1S
#90000
0-
0:
0S
#95000
13
05
b11000000000000000 A
0B
0C
b10000 D
b0100000000000000 E
1S
#100000
0,
19
1:
0S
#105000
b11100000000000000 A
b1010000000000000 E
1S
#110000
1*
18
0S
#115000
07
08
09
0:
b11110000000000000 A
b1101000000000000 E
0F
0G
b10000 H
1S
#120000
1#
1/
b01010 1
b00101 2
03
15
17
18
19
1:
b01000 ;
b01001 <
b01000 =
b00000000000000000 A
1B
1C
b00000 D
b0000000000000000 E
1F
1G
b00000 H
0S
#125000
1S
#130000
0#
10
0S
#135000
b00101 ;
b00101 <
b00101 =
b10000000000000000 A
b1000000000000000 E
b01000 I
b00000 O
b00000 P
0Q
b00000 R
1S
#140000
0/
0S
#145000
13
05
b11000000000000000 A
0B
0C
b10000 D
b1100000000000000 E
b00101 I
b01000 J
1S
#150000
1.
b00011 1
b00011 ;
0S
#155000
b01001 <
b01000 =
b11100000000000000 A
b1110000000000000 E
b00011 I
b00101 J
b01000 K
b01100 O
b01100 P
1Q
b00001 R
1S
#160000
0.
00
b01000 ;
0S
#165000
07
08
09
0:
b11110000000000000 A
b1111000000000000 E
0F
0G
b10000 H
1S
#170000
10
0S
#175000
b00101 ;
b00101 <
b00101 =
b11111000000000000 A
b0111100000000000 E
b01000 I
b00011 J
b00101 K
b01000 L
b00000 O
b00000 P
0Q
b00000 R
1S
#180000
0S
#185000
b01101 ;
b01101 <
b01101 =
b11111100000000000 A
b0011110000000000 E
b00101 I
b01000 J
b00011 K
b00101 L
b01000 M
b01000 O
1S
#190000
0S
#195000
03
15
17
18
19
1:
b00000 ;
b00000 <
b00000 =
b11111110000000000 A
1B
1C
b11000 D
b0001111000000000 E
1F
1G
b11000 H
b01101 I
b00101 J
b01000 K
b00011 L
b00101 M
b01000 N
b00101 O
1S
