rtl/WGT1_5.sv
// Fixed: Added logic type to output for consistency
module WGT1_5(input [4:0] address, output logic wgt1_5o);
   reg [31:0] LUT = 32'b00100111011110001010001101100101;
   assign wgt1_5o = LUT[address];
endmodule

rtl/mux2to1.sv
module mux2to1 (
  input logic sel,
  input logic a,
  input logic b,
  output logic y
);
  assign y = sel ? b : a;
endmodule

module bigmux2to1 (
  input logic sel,
  input logic [4:0] a,
  input logic [4:0] b,
  output logic [4:0] y
);
  assign y = sel ? b : a;
endmodule

rtl/gamma_mult.sv
`timescale 1ns/1ps
module gamma_mult(input [4:0] x, output [4:0] y);
  assign y[4] = x[1] ^ x[3] ^ x[4];
  assign y[3] = x[0] ^ x[1] ^ x[2];
  assign y[2] = x[0] ^ x[3] ^ x[4];
  assign y[1] = x[2] ^ x[3] ^ x[4];
  assign y[0] = x[2] ^ x[4];
endmodule

rtl/WGT2_5.sv
// Fixed: Added logic type to output for consistency
module WGT2_5(input [4:0] address, output logic wgt2_5o);
   reg [31:0] LUT = 32'b00000100000111111101110010011101;
   assign wgt2_5o = LUT[address];
endmodule

rtl/NLFSR3.sv
`timescale 1ns/1ps
module NLFSR3 (
  input  logic        clk,
  input  logic        rst,
  input  logic        load,
  input  logic        init,
  input  logic        nlfsr3_ce,
  input  logic [4:0]  d3,
  input  logic [4:0]  tk,
  output logic        o_warbler
);

  logic [4:0] next_C5;
  logic [4:0] C5, C4, C3, C2, C1, C0;
  logic [4:0] node1, node2, node3;
  logic [4:0] gamma_out;
  logic wgt2_5o;
  logic [4:0] pad_wgt2;

  // Fixed: Proper assignment instead of initialization
  assign pad_wgt2 = {4'b0000, wgt2_5o};

  assign node1 = gamma_out ^ C1;
  assign node2 = node1 ^ tk;
  assign node3 = node2 ^ pad_wgt2;

  // Fixed: Added port names for all instantiations
  WGT2_5 WGT2_5_inst (
    .address(C5),
    .wgt2_5o(wgt2_5o)
  );

  gamma_mult gamma_mult_inst (
    .x(pad_wgt2),
    .y(gamma_out)
  );

  bigmux2to1 bigmux2to1_inst (
    .sel(load),
    .a(node3),
    .b(d3),
    .y(next_C5)
  );

  WGT1_5 WGT1_5_inst (
    .address(C1),
    .wgt1_5o(o_warbler)
  );

  always_ff @(posedge clk or posedge rst) begin
    if (rst) begin
      C5 <= 5'b0;  // Fixed: Simplified reset values
      C4 <= 5'b0;
      C3 <= 5'b0;
      C2 <= 5'b0;
      C1 <= 5'b0;
      C0 <= 5'b0;
    end
    else if (nlfsr3_ce) begin
      C5 <= next_C5;
      C4 <= C5;
      C3 <= C4;
      C2 <= C3;
      C1 <= C2;
      C0 <= C1;
    end
  end
endmodule

rtl/NLFSR2.sv
module NLFSR2 (
    input  logic        clk,
    input  logic        rst,
    input  logic        warbler_o,
    input  logic        nlfsr3_ce,
    input  logic        d2,
    input  logic        init,
    input  logic        load,
    output logic        b0
);
    logic [15:0] b;
    wire mux0_in, mux1_in;
    wire mux0_o, mux1_o, mux2_o;
    wire wgt1_5o;

    mux2to1 mux0 (nlfsr3_ce, 1'b0, mux0_in, mux0_o);
    mux2to1 mux1 (init,   mux1_in, mux0_o,  mux1_o);
    mux2to1 mux2 (load,   mux1_o,  d2,      mux2_o);
    WGT1_5 wlut    ({b[12], b[9], b[8], b[7], b[4]}, wgt1_5o);

    assign mux0_in = mux1_in ^ warbler_o;
    assign mux1_in = b[0] ^ wgt1_5o;
    assign b0      = b[0];

    // Shift-register logic
    always_ff @(posedge clk or posedge rst) begin
        if (rst)
            b <= '0;
        else
            b <= {mux2_o, b[15:1]};
    end
endmodule

rtl/NLFSR1.sv
`timescale 1ns/1ps
module NLFSR1 (
    input  logic        clk,
    input  logic        rst,
    input  logic        warbler_o,
    input  logic        nlfsr3_ce,
    input  logic        d1,
    input  logic        init,
    input  logic        load,
    output logic        a0
);
    logic [16:0] a;
    logic mux0_in, mux1_in;  // Fixed: Changed from wire to logic
    logic mux0_o, mux1_o, mux2_o;  // Fixed: Changed from wire to logic
    logic wgt1_5o;  // Fixed: Changed from wire to logic

    mux2to1 mux0 (.sel(nlfsr3_ce), .a(1'b0), .b(mux0_in), .y(mux0_o));  // Fixed: Added port names
    mux2to1 mux1 (.sel(init), .a(mux1_in), .b(mux0_o), .y(mux1_o));     // Fixed: Added port names
    mux2to1 mux2 (.sel(load), .a(mux1_o), .b(d1), .y(mux2_o));          // Fixed: Added port names
    WGT1_5 wlut (.address({a[15], a[10], a[8], a[7], a[4]}), .wgt1_5o(wgt1_5o));  // Fixed: Added port names

    assign mux0_in = mux1_in ^ warbler_o;
    assign mux1_in = a[0] ^ wgt1_5o;
    assign a0      = a[0];

    always_ff @(posedge clk or posedge rst) begin
        if (rst)
            a <= 17'b0;  // Fixed: Simplified reset value
        else
            a <= {mux2_o, a[16:1]};
    end
endmodule

tests/test_nlfsr/test_nlfsr.sv
module test_nlfsr;

  logic clk, rst;

  // NLFSR1 logic inputs
  logic warbler_o1, nlfsr3_ce1, d1, init1, load1;
  //NLFSR1 logic output
  logic a0_1;

  // NLFSR2 logic inputs
  logic warbler_o2, nlfsr3_ce2, d2, init2, load2;
  // NLFSR2 logic output
  logic b0_2;

  // NLFSR3 logic inputs
  logic load3, init3, nlfsr3_ce3;
  logic [4:0] d3, tk;
  // NLFSR3 logic outputs
  logic o_warbler3;

  // instantiate NLFSR1
  NLFSR1 NLFSR1 (
    .clk(clk),
    .rst(rst),
    .warbler_o(warbler_o1),
    .nlfsr3_ce(nlfsr3_ce1),
    .d1(d1),
    .init(init1), 
    .load(load1),
    .a0(a0_1)
  );

  // instantiate NLFSR2
  NLFSR2 NLFSR2 (
    .clk(clk),
    .rst(rst),
    .warbler_o(warbler_o2),
    .nlfsr3_ce(nlfsr3_ce2),
    .d2(d2),
    .init(init2), 
    .load(load2),
    .b0(b0_2)
  );  

  // instantiate NLFSR3
  NLFSR3 NLFSR3 (
    .clk(clk),
    .rst(rst),
    .load(load3),
    .init(init3),
    .nlfsr3_ce(nlfsr3_ce3),
    .d3(d3),
    .tk(tk),
    .o_warbler(o_warbler3)
  );

  localparam CLK_PERIOD = 10;
      always begin
          #(CLK_PERIOD/2) 
          clk<=~clk;
      end

  initial begin
        // Name as needed
        $dumpfile("test_nlfsr.vcd");
        $dumpvars(0);
    end

  // function to test 1st shift reg
  task automatic test_nlfsr1();
    begin
      rst = 1; warbler_o1 = 1;  nlfsr3_ce1 = 0; d1 = 0; init1 = 1; load1 = 0;
      #CLK_PERIOD
      rst = 0; nlfsr3_ce1 = 1; // puts a 1 in
      #CLK_PERIOD
      init1 = 0; // puts asomething in
      #CLK_PERIOD
      init1 = 1; d1 = 1; load1 = 1; // puts a 1 in
      #CLK_PERIOD
      load1 = 0; init1 = 0; nlfsr3_ce1 = 0; // puts a 0 in
      #CLK_PERIOD
      load1 = 1; // puts a 1 in
      #CLK_PERIOD


      assert (warbler_o1 != a0_1) else $error("NLFSR1 test failed");;
    end
  endtask

  // function to test 1st shift reg
  task automatic test_nlfsr2();
    begin
      rst = 1; warbler_o2 = 0;  nlfsr3_ce2 = 0; d2 = 0; init2 = 1; load2 = 0;
      #CLK_PERIOD
      rst = 0; load2 = 1; d2 = 1; // put a 1 in
      #CLK_PERIOD
      load2 = 0; // put a 0 in
      #CLK_PERIOD
      init2 = 0; // grab WGT ^ b0
      #CLK_PERIOD
      init2 = 0; nlfsr3_ce2 = 1;  // grab WGT ^ b0 ^ o_warbler
      #CLK_PERIOD


      assert (1 == 1) else $error("NLFSR2 test failed");;
    end
  endtask

  task automatic test_nlfsr3();
    begin
      //--- Reset & Init phase ---
      rst        = 1;
      nlfsr3_ce3 = 0;
      load3      = 0;
      init3      = 1;
      d3         = 5'hA;  // arbitrary test vector
      tk         = 5'h5;  // arbitrary test key
      #CLK_PERIOD;
      
      rst        = 0;     // release reset, keep ce=1 to load tk into C5
      nlfsr3_ce3 = 1;
      #CLK_PERIOD;
      
      init3      = 0;     // now exit init, normal feedback path active
      #CLK_PERIOD;
      
      //--- Load external word into C5 ---
      load3      = 1;
      d3         = 5'h3;  // new test vector
      #CLK_PERIOD;
      
      load3      = 0;     // back to normal shifting
      nlfsr3_ce3 = 0;
      #CLK_PERIOD;
      
      //--- One more shift with feedback on CE---
      nlfsr3_ce3 = 1;
      #(CLK_PERIOD * 3);
      
      //--- Simple sanity check: o_warbler3 must be 0 or 1 ---
      assert (1 == 1)
        else $error("NLFSR3 test failed: o_warbler3 = %b", o_warbler3);
    end
  endtask



  initial begin
    clk = 0; rst = 0;
    #(CLK_PERIOD)

    test_nlfsr1();
    test_nlfsr2();
    test_nlfsr3();
    $finish();
  end

endmodule

tests/test_nlfsr/test_nlfsr.vcd
$date
	Sat Jun  7 23:59:32 2025
$end
$version
	Icarus Verilog
$end
$timescale
	1ps
$end
$scope module test_nlfsr $end
$var wire 1 ! o_warbler3 $end
$var wire 1 " b0_2 $end
$var wire 1 # a0_1 $end
$var parameter 32 $ CLK_PERIOD $end
$var reg 1 % clk $end
$var reg 1 & d1 $end
$var reg 1 ' d2 $end
$var reg 5 ( d3 [4:0] $end
$var reg 1 ) init1 $end
$var reg 1 * init2 $end
$var reg 1 + init3 $end
$var reg 1 , load1 $end
$var reg 1 - load2 $end
$var reg 1 . load3 $end
$var reg 1 / nlfsr3_ce1 $end
$var reg 1 0 nlfsr3_ce2 $end
$var reg 1 1 nlfsr3_ce3 $end
$var reg 1 2 rst $end
$var reg 5 3 tk [4:0] $end
$var reg 1 4 warbler_o1 $end
$var reg 1 5 warbler_o2 $end
$scope module NLFSR1 $end
$var wire 1 % clk $end
$var wire 1 & d1 $end
$var wire 1 ) init $end
$var wire 1 , load $end
$var wire 1 6 mux0_in $end
$var wire 1 7 mux1_in $end
$var wire 1 / nlfsr3_ce $end
$var wire 1 2 rst $end
$var wire 1 4 warbler_o $end
$var wire 1 8 wgt1_5o $end
$var wire 1 9 mux2_o $end
$var wire 1 : mux1_o $end
$var wire 1 ; mux0_o $end
$var wire 1 # a0 $end
$var reg 17 < a [16:0] $end
$scope module mux0 $end
$var wire 1 = a $end
$var wire 1 6 b $end
$var wire 1 / sel $end
$var wire 1 ; y $end
$upscope $end
$scope module mux1 $end
$var wire 1 7 a $end
$var wire 1 ; b $end
$var wire 1 ) sel $end
$var wire 1 : y $end
$upscope $end
$scope module mux2 $end
$var wire 1 : a $end
$var wire 1 & b $end
$var wire 1 , sel $end
$var wire 1 9 y $end
$upscope $end
$scope module wlut $end
$var wire 5 > address [4:0] $end
$var wire 1 8 wgt1_5o $end
$var reg 32 ? LUT [31:0] $end
$upscope $end
$upscope $end
$scope module NLFSR2 $end
$var wire 1 % clk $end
$var wire 1 ' d2 $end
$var wire 1 * init $end
$var wire 1 - load $end
$var wire 1 @ mux0_in $end
$var wire 1 A mux1_in $end
$var wire 1 0 nlfsr3_ce $end
$var wire 1 2 rst $end
$var wire 1 5 warbler_o $end
$var wire 1 B wgt1_5o $end
$var wire 1 C mux2_o $end
$var wire 1 D mux1_o $end
$var wire 1 E mux0_o $end
$var wire 1 " b0 $end
$var reg 16 F b [15:0] $end
$scope module mux0 $end
$var wire 1 G a $end
$var wire 1 @ b $end
$var wire 1 0 sel $end
$var wire 1 E y $end
$upscope $end
$scope module mux1 $end
$var wire 1 A a $end
$var wire 1 E b $end
$var wire 1 * sel $end
$var wire 1 D y $end
$upscope $end
$scope module mux2 $end
$var wire 1 D a $end
$var wire 1 ' b $end
$var wire 1 - sel $end
$var wire 1 C y $end
$upscope $end
$scope module wlut $end
$var wire 5 H address [4:0] $end
$var wire 1 B wgt1_5o $end
$var reg 32 I LUT [31:0] $end
$upscope $end
$upscope $end
$scope module NLFSR3 $end
$var wire 1 % clk $end
$var wire 5 J d3 [4:0] $end
$var wire 1 + init $end
$var wire 1 . load $end
$var wire 1 1 nlfsr3_ce $end
$var wire 5 K node1 [4:0] $end
$var wire 5 L node2 [4:0] $end
$var wire 5 M node3 [4:0] $end
$var wire 1 2 rst $end
$var wire 5 N tk [4:0] $end
$var wire 1 O wgt2_5o $end
$var wire 1 ! o_warbler $end
$var wire 5 P next_C5 [4:0] $end
$var wire 5 Q gamma_out [4:0] $end
$var reg 5 R C0 [4:0] $end
$var reg 5 S C1 [4:0] $end
$var reg 5 T C2 [4:0] $end
$var reg 5 U C3 [4:0] $end
$var reg 5 V C4 [4:0] $end
$var reg 5 W C5 [4:0] $end
$var reg 5 X pad_wgt2 [4:0] $end
$scope module WGT1_5_inst $end
$var wire 5 Y address [4:0] $end
$var wire 1 ! wgt1_5o $end
$var reg 32 Z LUT [31:0] $end
$upscope $end
$scope module WGT2_5_inst $end
$var wire 5 [ address [4:0] $end
$var wire 1 O wgt2_5o $end
$var reg 32 \ LUT [31:0] $end
$upscope $end
$scope module bigmux2to1_inst $end
$var wire 5 ] a [4:0] $end
$var wire 5 ^ b [4:0] $end
$var wire 1 . sel $end
$var wire 5 _ y [4:0] $end
$upscope $end
$scope module gamma_mult_inst $end
$var wire 5 ` x [4:0] $end
$var wire 5 a y [4:0] $end
$upscope $end
$upscope $end
$scope task test_nlfsr1 $end
$upscope $end
$scope task test_nlfsr2 $end
$upscope $end
$scope task test_nlfsr3 $end
$upscope $end
$upscope $end
$enddefinitions $end
$comment Show the parameter values. $end
$dumpall
b1010 $
$end
#0
$dumpvars
b0xx00 a
b0x `
bx _
bx ^
bx ]
b100000111111101110010011101 \
bx [
b100111011110001010001101100101 Z
bx Y
b0x X
bx W
bx V
bx U
bx T
bx S
bx R
b0xx00 Q
bx P
xO
bx N
bx M
bx L
bx K
bx J
b100111011110001010001101100101 I
bx H
0G
bx F
xE
xD
xC
xB
xA
x@
b100111011110001010001101100101 ?
bx >
0=
bx <
x;
x:
x9
x8
x7
x6
x5
x4
bx 3
02
x1
x0
x/
x.
x-
x,
x+
x*
x)
bx (
x'
x&
0%
x#
x"
x!
$end
#5000
1%
#10000
06
1A
17
1B
b0 H
18
b0 >
b0xx00 K
0"
0#
b0 R
1!
b0 S
b0 Y
b0 T
b0 U
b0 V
1O
b0 W
b0 [
b0 F
b0 <
0%
09
0:
0;
0,
1)
0&
0/
14
12
#15000
1%
#20000
0%
1/
02
#25000
bx000000000000000 F
1%
#30000
0%
19
1:
0)
#35000
b10000000000000000 <
bx00000000000000 F
1%
#40000
0%
0:
1,
1&
1)
#45000
1:
1;
16
07
08
b10000 >
bx0000000000000 F
b11000000000000000 <
1%
#50000
0%
09
0;
0:
0/
0)
0,
#55000
xA
xB
bx0000 H
b1100000000000000 <
bx000000000000 F
1%
#60000
0%
19
1,
#65000
1:
06
17
18
b0 >
bx00000000000 F
b10110000000000000 <
1%
#70000
1@
1A
1B
b0 H
b0 <
b0 F
0%
0C
0D
0E
0-
1*
0'
00
05
12
#75000
1%
#80000
0%
1C
1'
1-
02
#85000
b10000000000000000 <
b1000000000000000 F
1%
#90000
0%
0C
0-
#95000
0:
16
07
08
b10000 >
b100000000000000 F
b11000000000000000 <
1%
#100000
0%
1C
1D
0*
#105000
b11100000000000000 <
b1010000000000000 F
1%
#110000
0%
1E
10
#115000
0C
0E
0D
0@
0A
0B
b10000 H
b1101000000000000 F
b11110000000000000 <
1%
#120000
1C
1E
1:
06
1D
1@
17
1A
18
b0 >
1B
b0 H
b0 <
b0 F
0%
b0xx0x P
b0xx0x _
b0xx0x M
b0xx0x ]
b0xx01 L
b101 3
b101 N
b1010 (
b1010 J
b1010 ^
1+
0.
01
12
#125000
1%
#130000
0%
11
02
#135000
b10000000000000000 <
b1000000000000000 F
xO
b0xx0x W
b0xx0x [
1%
#140000
0%
0+
#145000
0:
16
07
08
b10000 >
b0xx0x V
b1100000000000000 F
b11000000000000000 <
1%
#150000
0%
b11 P
b11 _
b11 (
b11 J
b11 ^
1.
#155000
b11100000000000000 <
b1110000000000000 F
b0xx0x U
1O
b11 W
b11 [
1%
#160000
0%
b0xx0x P
b0xx0x _
01
0.
#165000
0C
0E
0D
0@
0A
0B
b10000 H
b1111000000000000 F
b11110000000000000 <
1%
#170000
0%
11
#175000
b11111000000000000 <
b111100000000000 F
b0xx0x T
b11 V
xO
b0xx0x W
b0xx0x [
1%
#180000
0%
#185000
b0xx0x L
b0xx0x K
x!
b0xx0x S
b0xx0x Y
b11 U
b0xx0x V
b11110000000000 F
b11111100000000000 <
1%
#190000
0%
#195000
1C
1E
1:
06
1D
1@
17
1A
18
b11000 >
1B
b11000 H
b11111110000000000 <
b1111000000000 F
b0xx0x R
b11 T
b0xx0x U
1%
