rtl/bit_collector.sv
module bit_collector (
    input  logic clk,
    input  logic rst,
    input  logic enable,         // When high, collector is active
    input  logic o_valid,        // From TRNG
    input  logic o_warbler,      // From TRNG

    output logic byte_ready,     // High when a full byte is collected
    output logic [7:0] rand_byte // Collected random byte
);

    logic [7:0] shift_reg;
    logic [2:0] bit_count;

    always_ff @(posedge clk or posedge rst) begin
        if (rst) begin
            shift_reg  <= 8'b0;
            bit_count  <= 3'd0;
            rand_byte  <= 8'b0;
            byte_ready <= 1'b0;
        end else if (enable && o_valid) begin
            shift_reg <= {shift_reg[6:0], o_warbler};
            bit_count <= bit_count + 1;

            if (bit_count == 3'd7) begin
                rand_byte  <= {shift_reg[6:0], o_warbler};
                byte_ready <= 1'b1;
                bit_count  <= 3'd0;
            end else begin
                byte_ready <= 1'b0;
            end
        end else begin
            byte_ready <= 1'b0;
        end
    end

endmodule

rtl/WGT1_5.sv
// Fixed: Added logic type to output for consistency
module WGT1_5(input [4:0] address, output logic wgt1_5o);
   reg [31:0] LUT = 32'b00100111011110001010001101100101;
   assign wgt1_5o = LUT[address];
endmodule

rtl/mux2to1.sv
module mux2to1 (
  input logic sel,
  input logic a,
  input logic b,
  output logic y
);
  assign y = sel ? b : a;
endmodule

module bigmux2to1 (
  input logic sel,
  input logic [4:0] a,
  input logic [4:0] b,
  output logic [4:0] y
);
  assign y = sel ? b : a;
endmodule

rtl/gamma_mult.sv
`timescale 1ns/1ps
module gamma_mult(input [4:0] x, output [4:0] y);
  assign y[4] = x[1] ^ x[3] ^ x[4];
  assign y[3] = x[0] ^ x[1] ^ x[2];
  assign y[2] = x[0] ^ x[3] ^ x[4];
  assign y[1] = x[2] ^ x[3] ^ x[4];
  assign y[0] = x[2] ^ x[4];
endmodule

rtl/WGT2_5.sv
// Fixed: Added logic type to output for consistency
module WGT2_5(input [4:0] address, output logic wgt2_5o);
   reg [31:0] LUT = 32'b00000100000111111101110010011101;
   assign wgt2_5o = LUT[address];
endmodule

rtl/NLFSR3.sv
`timescale 1ns/1ps
module NLFSR3 (
  input  logic        clk,
  input  logic        rst,
  input  logic        load,
  input  logic        init,
  input  logic        nlfsr3_ce,
  input  logic [4:0]  d3,
  input  logic [4:0]  tk,
  output logic        o_warbler
);

  logic [4:0] next_C5;
  logic [4:0] C5, C4, C3, C2, C1, C0;
  logic [4:0] node1, node2, node3;
  logic [4:0] gamma_out;
  logic wgt2_5o;
  logic [4:0] pad_wgt2;

  // Fixed: Proper assignment instead of initialization
  assign pad_wgt2 = {4'b0000, wgt2_5o};

  assign node1 = gamma_out ^ C1;
  assign node2 = node1 ^ tk;
  assign node3 = node2 ^ pad_wgt2;

  // Fixed: Added port names for all instantiations
  WGT2_5 WGT2_5_inst (
    .address(C5),
    .wgt2_5o(wgt2_5o)
  );

  gamma_mult gamma_mult_inst (
    .x(pad_wgt2),
    .y(gamma_out)
  );

  bigmux2to1 bigmux2to1_inst (
    .sel(load),
    .a(node3),
    .b(d3),
    .y(next_C5)
  );

  WGT1_5 WGT1_5_inst (
    .address(C1),
    .wgt1_5o(o_warbler)
  );

  always_ff @(posedge clk or posedge rst) begin
    if (rst) begin
      C5 <= 5'b0;  // Fixed: Simplified reset values
      C4 <= 5'b0;
      C3 <= 5'b0;
      C2 <= 5'b0;
      C1 <= 5'b0;
      C0 <= 5'b0;
    end
    else if (nlfsr3_ce) begin
      C5 <= next_C5;
      C4 <= C5;
      C3 <= C4;
      C2 <= C3;
      C1 <= C2;
      C0 <= C1;
    end
  end
endmodule

rtl/shift5.sv
// input is xor a0 and b0
`timescale 1ns/1ps
module shift5 (
    input  logic        clk,
    input  logic        rst,
    input  logic        in_bit,
    output logic [4:0]  s
);
    always_ff @(posedge clk or posedge rst) begin
        if (rst)
            s <= 5'b0;
        else
            s <= {s[3:0], in_bit};
    end
endmodule

rtl/NLFSR2.sv
module NLFSR2 (
    input  logic        clk,
    input  logic        rst,
    input  logic        warbler_o,
    input  logic        nlfsr3_ce,
    input  logic        d2,
    input  logic        init,
    input  logic        load,
    output logic        b0
);
    logic [15:0] b;
    wire mux0_in, mux1_in;
    wire mux0_o, mux1_o, mux2_o;
    wire wgt1_5o;

    mux2to1 mux0 (nlfsr3_ce, 1'b0, mux0_in, mux0_o);
    mux2to1 mux1 (init,   mux1_in, mux0_o,  mux1_o);
    mux2to1 mux2 (load,   mux1_o,  d2,      mux2_o);
    WGT1_5 wlut    ({b[12], b[9], b[8], b[7], b[4]}, wgt1_5o);

    assign mux0_in = mux1_in ^ warbler_o;
    assign mux1_in = b[0] ^ wgt1_5o;
    assign b0      = b[0];

    // Shift-register logic
    always_ff @(posedge clk or posedge rst) begin
        if (rst)
            b <= '0;
        else
            b <= {mux2_o, b[15:1]};
    end
endmodule

rtl/NLFSR1.sv
`timescale 1ns/1ps
module NLFSR1 (
    input  logic        clk,
    input  logic        rst,
    input  logic        warbler_o,
    input  logic        nlfsr3_ce,
    input  logic        d1,
    input  logic        init,
    input  logic        load,
    output logic        a0
);
    logic [16:0] a;
    logic mux0_in, mux1_in;  // Fixed: Changed from wire to logic
    logic mux0_o, mux1_o, mux2_o;  // Fixed: Changed from wire to logic
    logic wgt1_5o;  // Fixed: Changed from wire to logic

    mux2to1 mux0 (.sel(nlfsr3_ce), .a(1'b0), .b(mux0_in), .y(mux0_o));  // Fixed: Added port names
    mux2to1 mux1 (.sel(init), .a(mux1_in), .b(mux0_o), .y(mux1_o));     // Fixed: Added port names
    mux2to1 mux2 (.sel(load), .a(mux1_o), .b(d1), .y(mux2_o));          // Fixed: Added port names
    WGT1_5 wlut (.address({a[15], a[10], a[8], a[7], a[4]}), .wgt1_5o(wgt1_5o));  // Fixed: Added port names

    assign mux0_in = mux1_in ^ warbler_o;
    assign mux1_in = a[0] ^ wgt1_5o;
    assign a0      = a[0];

    always_ff @(posedge clk or posedge rst) begin
        if (rst)
            a <= 17'b0;  // Fixed: Simplified reset value
        else
            a <= {mux2_o, a[16:1]};
    end
endmodule

rtl/fsm.sv
module fsm (
    input  logic clk,
    input  logic rst,
    output logic load_en,
    output logic init_en,
    output logic run_en,
    output logic nlfsr3_ce,
    output logic output_en
);

    // State encoding (one-hot): LOAD=100, INIT=010, RUN=001
    localparam logic [2:0]
        LOAD = 3'b100,
        INIT = 3'b010,
        RUN  = 3'b001;

    logic [2:0] state;
    logic [5:0] cnt;

    // Sequential state and counter updates
    always_ff @(posedge clk or posedge rst) begin
        if (rst) begin
            state <= LOAD;
            cnt   <= 6'd0;
        end else begin
            case (state)
                LOAD: begin
                    if (cnt == 6'd17) begin    // 18 cycles for loading citeturn0file0
                        state <= INIT;
                        cnt   <= 6'd0;
                    end else begin
                        state <= LOAD;
                        cnt   <= cnt + 6'd1;
                    end
                end

                INIT: begin
                    if (cnt == 6'd35) begin    // 36 cycles for initialization citeturn0file0
                        state <= RUN;
                        cnt   <= 6'd0;
                    end else begin
                        state <= INIT;
                        cnt   <= cnt + 6'd1;
                    end
                end

                RUN: begin
                    state <= RUN;
                    cnt   <= cnt + 6'd1;       // free-running counter for mod-5 CE
                end

                default: begin
                    state <= LOAD;
                    cnt   <= 6'd0;
                end
            endcase
        end
    end

    // Output enables for each state
    assign load_en = (state == LOAD);
    assign init_en = (state == INIT);
    assign run_en  = (state == RUN);

    // NLFSR3 chip-enable: high during LOAD;
    // during INIT except first cycle; during RUN when cnt mod 5 == 4
    always_comb begin
        if (load_en) begin
            nlfsr3_ce = 1'b1;
            output_en = 1'b0;
        end else if (init_en) begin
            output_en = 1'b0;
            nlfsr3_ce = (cnt != 6'd0);
        end else begin
            nlfsr3_ce = (cnt % 6'd5 == 6'd4);
            output_en = 1'b1;
        end
    end

endmodule

rtl/trng.sv
module trng (
    input  logic        clk,
    input  logic        rst,
    input  logic        d1,
    input  logic        d2,
    input  logic [4:0]  d3,
    output logic        o_valid,
    output logic        o_warbler
);
    logic load_en, init_en, run_en, nlfsr3_ce;
    logic a0, b0;
    logic [4:0] s;
    logic warbler_bit; // Internal 1-bit signal for the output
    logic output_en;

    // FSM
    fsm fsm (.clk(clk), .rst(rst), .load_en(load_en), .init_en(init_en), .run_en(run_en), .nlfsr3_ce(nlfsr3_ce), .output_en(output_en));
    
    // NLFSRs and shift register
    NLFSR1 nlfsr1 (.clk(clk), .rst(rst), .warbler_o(warbler_bit), .nlfsr3_ce(nlfsr3_ce), .d1(d1), .init(init_en), .load(load_en), .a0(a0));
    NLFSR2 nlfsr2 (.clk(clk), .rst(rst), .warbler_o(warbler_bit), .nlfsr3_ce(nlfsr3_ce), .d2(d2), .init(init_en), .load(load_en), .b0(b0));
    shift5 shift5 (.clk(clk), .rst(rst), .in_bit(a0 ^ b0), .s(s));
    NLFSR3 nlfsr3 (.clk(clk), .rst(rst), .load(load_en), .init(init_en), .nlfsr3_ce(nlfsr3_ce), .d3(d3), .tk(s), .o_warbler(warbler_bit));

    // Connect the internal warbler bit to the output
    assign o_warbler = warbler_bit;
    
    // valid output = NLFSR3 chip-enable
    assign o_valid = nlfsr3_ce & output_en;
endmodule

tests/test_bitcollect/test_bitcollect.sv
`timescale 1ns/1ps
module test_bitcollect;
  // Common signals
  logic clk, rst;

  // Localparam for clock period
  localparam CLK_PERIOD = 10;

  // Clock generation
  always begin
    #(CLK_PERIOD/2) clk <= ~clk;
  end

  // Waveform generation
  initial begin
    $dumpfile("test_bitcollect.vcd");
    $dumpvars(0, test_bitcollect);
  end

  // =========== TRNG + Bit Collector Integration Test ===========

  // TRNG interface
  logic trng_d1, trng_d2, trng_o_valid, trng_o_warbler;
  logic [4:0] trng_d3;

  // Bit Collector interface
  logic byte_ready;
  logic [7:0] rand_byte;

  // Instantiate TRNG
  trng trng_inst (
    .clk(clk),
    .rst(rst),
    .d1(trng_d1),
    .d2(trng_d2),
    .d3(trng_d3),
    .o_valid(trng_o_valid),
    .o_warbler(trng_o_warbler)
  );

  // Instantiate Bit Collector
  bit_collector collector (
    .clk(clk),
    .rst(rst),
    .enable(1'b1),
    .o_valid(trng_o_valid),
    .o_warbler(trng_o_warbler),
    .byte_ready(byte_ready),
    .rand_byte(rand_byte)
  );

  // Task to run the TRNG + collector system
  task automatic test_trng_collector_operation();
    begin
      // Initialize TRNG inputs
      trng_d1 = 1'b0;
      trng_d2 = 1'b1;
      trng_d3 = 5'b11001;

      // Reset TRNG and collector
      rst = 1'b1;
      #CLK_PERIOD;
      rst = 1'b0;

      // Wait through FSM startup
      repeat(200) @(posedge clk);
      repeat(64) @(posedge clk);  // INIT + RUN entry delay

      // Collect and display a few random bytes
      repeat(1000) @(posedge clk);
    end
  endtask

  // Monitor output from collector
  always_ff @(posedge clk) begin
    if (byte_ready) begin
      $display("Collected Byte: 0x%02x at time %0t", rand_byte, $time);
    end
  end

  // Main test sequence
  initial begin
    // Initialize signals
    clk = 0;
    rst = 1;

    // Begin test
    #(CLK_PERIOD * 2);
    rst = 0;
    #CLK_PERIOD;

    $display("Testing TRNG + Bit Collector integration...");
    test_trng_collector_operation();

    #(CLK_PERIOD * 20);
    $display("TRNG + Bit Collector test completed!");
    $finish();
  end

endmodule

tests/test_bitcollect/test_bitcollect.vcd
$version Generated by VerilatedVcd $end
$timescale 1ps $end
 $scope module $rootio $end
 $upscope $end
 $scope module test_bitcollect $end
  $var wire 1 N clk $end
  $var wire 1 O rst $end
  $var wire 32 V CLK_PERIOD [31:0] $end
  $var wire 1 P trng_d1 $end
  $var wire 1 Q trng_d2 $end
  $var wire 1 = trng_o_valid $end
  $var wire 1 > trng_o_warbler $end
  $var wire 5 R trng_d3 [4:0] $end
  $var wire 1 ? byte_ready $end
  $var wire 8 @ rand_byte [7:0] $end
  $scope module collector $end
   $var wire 1 N clk $end
   $var wire 1 O rst $end
   $var wire 1 W enable $end
   $var wire 1 = o_valid $end
   $var wire 1 > o_warbler $end
   $var wire 1 ? byte_ready $end
   $var wire 8 @ rand_byte [7:0] $end
   $var wire 8 A shift_reg [7:0] $end
   $var wire 3 B bit_count [2:0] $end
  $upscope $end
  $scope module trng_inst $end
   $var wire 1 N clk $end
   $var wire 1 O rst $end
   $var wire 1 P d1 $end
   $var wire 1 Q d2 $end
   $var wire 5 R d3 [4:0] $end
   $var wire 1 = o_valid $end
   $var wire 1 > o_warbler $end
   $var wire 1 # load_en $end
   $var wire 1 $ init_en $end
   $var wire 1 % run_en $end
   $var wire 1 C nlfsr3_ce $end
   $var wire 1 & a0 $end
   $var wire 1 ' b0 $end
   $var wire 5 ( s [4:0] $end
   $var wire 1 > warbler_bit $end
   $var wire 1 D output_en $end
   $scope module fsm $end
    $var wire 1 N clk $end
    $var wire 1 O rst $end
    $var wire 1 # load_en $end
    $var wire 1 $ init_en $end
    $var wire 1 % run_en $end
    $var wire 1 C nlfsr3_ce $end
    $var wire 1 D output_en $end
    $var wire 3 X LOAD [2:0] $end
    $var wire 3 Y INIT [2:0] $end
    $var wire 3 Z RUN [2:0] $end
    $var wire 3 ) state [2:0] $end
    $var wire 6 * cnt [5:0] $end
   $upscope $end
   $scope module nlfsr1 $end
    $var wire 1 N clk $end
    $var wire 1 O rst $end
    $var wire 1 > warbler_o $end
    $var wire 1 C nlfsr3_ce $end
    $var wire 1 P d1 $end
    $var wire 1 $ init $end
    $var wire 1 # load $end
    $var wire 1 & a0 $end
    $var wire 17 + a [16:0] $end
    $var wire 1 5 mux0_in $end
    $var wire 1 , mux1_in $end
    $var wire 1 6 mux0_o $end
    $var wire 1 7 mux1_o $end
    $var wire 1 S mux2_o $end
    $var wire 1 - wgt1_5o $end
    $scope module mux0 $end
     $var wire 1 C sel $end
     $var wire 1 [ a $end
     $var wire 1 5 b $end
     $var wire 1 6 y $end
    $upscope $end
    $scope module mux1 $end
     $var wire 1 $ sel $end
     $var wire 1 , a $end
     $var wire 1 6 b $end
     $var wire 1 7 y $end
    $upscope $end
    $scope module mux2 $end
     $var wire 1 # sel $end
     $var wire 1 7 a $end
     $var wire 1 P b $end
     $var wire 1 S y $end
    $upscope $end
    $scope module wlut $end
     $var wire 5 . address [4:0] $end
     $var wire 1 - wgt1_5o $end
     $var wire 32 \ LUT [31:0] $end
    $upscope $end
   $upscope $end
   $scope module nlfsr2 $end
    $var wire 1 N clk $end
    $var wire 1 O rst $end
    $var wire 1 > warbler_o $end
    $var wire 1 C nlfsr3_ce $end
    $var wire 1 Q d2 $end
    $var wire 1 $ init $end
    $var wire 1 # load $end
    $var wire 1 ' b0 $end
    $var wire 16 / b [15:0] $end
    $var wire 1 8 mux0_in $end
    $var wire 1 0 mux1_in $end
    $var wire 1 9 mux0_o $end
    $var wire 1 : mux1_o $end
    $var wire 1 T mux2_o $end
    $var wire 1 1 wgt1_5o $end
    $scope module mux0 $end
     $var wire 1 C sel $end
     $var wire 1 [ a $end
     $var wire 1 8 b $end
     $var wire 1 9 y $end
    $upscope $end
    $scope module mux1 $end
     $var wire 1 $ sel $end
     $var wire 1 0 a $end
     $var wire 1 9 b $end
     $var wire 1 : y $end
    $upscope $end
    $scope module mux2 $end
     $var wire 1 # sel $end
     $var wire 1 : a $end
     $var wire 1 Q b $end
     $var wire 1 T y $end
    $upscope $end
    $scope module wlut $end
     $var wire 5 2 address [4:0] $end
     $var wire 1 1 wgt1_5o $end
     $var wire 32 \ LUT [31:0] $end
    $upscope $end
   $upscope $end
   $scope module nlfsr3 $end
    $var wire 1 N clk $end
    $var wire 1 O rst $end
    $var wire 1 # load $end
    $var wire 1 $ init $end
    $var wire 1 C nlfsr3_ce $end
    $var wire 5 R d3 [4:0] $end
    $var wire 5 ( tk [4:0] $end
    $var wire 1 > o_warbler $end
    $var wire 5 U next_C5 [4:0] $end
    $var wire 5 E C5 [4:0] $end
    $var wire 5 F C4 [4:0] $end
    $var wire 5 G C3 [4:0] $end
    $var wire 5 H C2 [4:0] $end
    $var wire 5 I C1 [4:0] $end
    $var wire 5 3 C0 [4:0] $end
    $var wire 5 J node1 [4:0] $end
    $var wire 5 ; node2 [4:0] $end
    $var wire 5 < node3 [4:0] $end
    $var wire 5 K gamma_out [4:0] $end
    $var wire 1 L wgt2_5o $end
    $var wire 5 M pad_wgt2 [4:0] $end
    $scope module WGT1_5_inst $end
     $var wire 5 I address [4:0] $end
     $var wire 1 > wgt1_5o $end
     $var wire 32 \ LUT [31:0] $end
    $upscope $end
    $scope module WGT2_5_inst $end
     $var wire 5 E address [4:0] $end
     $var wire 1 L wgt2_5o $end
     $var wire 32 ] LUT [31:0] $end
    $upscope $end
    $scope module bigmux2to1_inst $end
     $var wire 1 # sel $end
     $var wire 5 < a [4:0] $end
     $var wire 5 R b [4:0] $end
     $var wire 5 U y [4:0] $end
    $upscope $end
    $scope module gamma_mult_inst $end
     $var wire 5 M x [4:0] $end
     $var wire 5 K y [4:0] $end
    $upscope $end
   $upscope $end
   $scope module shift5 $end
    $var wire 1 N clk $end
    $var wire 1 O rst $end
    $var wire 1 4 in_bit $end
    $var wire 5 ( s [4:0] $end
   $upscope $end
  $upscope $end
 $upscope $end
$enddefinitions $end


#0
0#
0$
0%
0&
0'
b00000 (
b000 )
b000000 *
b00000000000000000 +
1,
1-
b00000 .
b0000000000000000 /
10
11
b00000 2
b00000 3
04
05
06
17
08
09
1:
b01100 ;
b01101 <
0=
1>
0?
b00000000 @
b00000000 A
b000 B
0C
1D
b00000 E
b00000 F
b00000 G
b00000 H
b00000 I
b01100 J
b01100 K
1L
b00001 M
0N
1O
0P
0Q
b00000 R
1S
1T
b01101 U
b00000000000000000000000000001010 V
1W
b100 X
b010 Y
b001 Z
0[
b00100111011110001010001101100101 \
b00000100000111111101110010011101 ]
#5000
1#
b100 )
1C
0D
1N
0S
0T
b00000 U
#10000
0N
#15000
1N
#20000
0N
0O
#25000
b000001 *
1N
#30000
b000000 *
0N
1O
1Q
b11001 R
1T
b11001 U
#35000
1N
#40000
0N
0O
#45000
b000001 *
b1000000000000000 /
b00000 ;
b00000 <
b11001 E
b00000 J
b00000 K
0L
b00000 M
1N
#50000
0N
#55000
b000010 *
b1100000000000000 /
b11001 F
1N
#60000
0N
#65000
b000011 *
b1110000000000000 /
b11001 G
1N
#70000
0N
#75000
b000100 *
b1111000000000000 /
00
01
b10000 2
18
19
0:
b11001 H
1N
#80000
0N
#85000
b000101 *
b1111100000000000 /
b11001 ;
b11001 <
b11001 I
b11001 J
1N
#90000
0N
#95000
b000110 *
b1111110000000000 /
b11001 3
1N
#100000
0N
#105000
b000111 *
b1111111000000000 /
10
11
b11000 2
08
09
1:
1N
#110000
0N
#115000
b001000 *
b1111111100000000 /
00
01
b11100 2
18
19
0:
1N
#120000
0N
#125000
b001001 *
b1111111110000000 /
b11110 2
1N
#130000
0N
#135000
b001010 *
b1111111111000000 /
1N
#140000
0N
#145000
b001011 *
b1111111111100000 /
1N
#150000
0N
#155000
b001100 *
b1111111111110000 /
b11111 2
1N
#160000
0N
#165000
b001101 *
b1111111111111000 /
1N
#170000
0N
#175000
b001110 *
b1111111111111100 /
1N
#180000
0N
#185000
b001111 *
b1111111111111110 /
1N
#190000
0N
#195000
1'
b010000 *
b1111111111111111 /
10
14
08
09
1:
1N
#200000
0N
#205000
b00001 (
b010001 *
b11000 ;
b11000 <
1N
#210000
0N
#215000
0#
1$
b00011 (
b010 )
b000000 *
07
0:
b11010 ;
b11010 <
0C
1N
0T
b11010 U
#220000
0N
#225000
b00111 (
b000001 *
b0111111111111111 /
b11110 ;
b11110 <
1C
1N
b11110 U
#230000
0N
#235000
b01111 (
b000010 *
b0011111111111111 /
b10110 ;
b10110 <
b11110 E
1N
b10110 U
#240000
0N
#245000
b11111 (
b000011 *
b0001111111111111 /
b00110 ;
b00110 <
b10110 E
b11110 F
1N
b00110 U
#250000
0N
#255000
b000100 *
b0000111111111111 /
00
11
b01111 2
18
19
1:
b00110 E
b10110 F
b11110 G
1N
1T
#260000
0N
#265000
b000101 *
b1000011111111111 /
b00110 F
b10110 G
b11110 H
1N
#270000
0N
#275000
b000110 *
b1100001111111111 /
15
16
17
08
09
0:
b00001 ;
b00001 <
0>
b00110 G
b10110 H
b11110 I
b11110 J
1N
1S
0T
b00001 U
#280000
0N
#285000
b000111 *
b10000000000000000 +
b0110000111111111 /
10
01
b00111 2
b11110 3
05
06
07
b01001 ;
b01001 <
1>
b00001 E
b00110 H
b10110 I
b10110 J
1N
0S
b01001 U
#290000
0N
#295000
b001000 *
b01000000000000000 +
0,
0-
b10000 .
b0011000011111111 /
00
11
b10011 2
b10110 3
15
16
17
18
19
1:
b11001 ;
b11001 <
b01001 E
b00001 F
b00110 I
b00110 J
1N
1S
1T
b11001 U
#300000
0N
#305000
b001001 *
b10100000000000000 +
1,
1-
b00000 .
b1001100001111111 /
10
01
b10001 2
b00110 3
05
06
07
08
09
0:
b11001 E
b01001 F
b00001 G
1N
0S
0T
#310000
0N
#315000
b001010 *
b01010000000000000 +
0,
0-
b10000 .
b0100110000111111 /
b00001 2
15
16
17
b11001 F
b01001 G
b00001 H
1N
1S
#320000
0N
#325000
b001011 *
b10101000000000000 +
1,
1-
b00000 .
b0010011000011111 /
00
11
b01001 2
b11110 ;
b11110 <
0>
b11001 G
b01001 H
b00001 I
b00001 J
1N
b11110 U
#330000
0N
#335000
b001100 *
b11010100000000000 +
0,
0-
b10000 .
b0001001100001111 /
10
01
b11100 2
b00001 3
b10110 ;
b10110 <
1>
b11110 E
b11001 H
b01001 I
b01001 J
1N
b10110 U
#340000
0N
#345000
b001101 *
b11101010000000000 +
1,
1-
b11000 .
b0000100110000111 /
00
11
b00110 2
b01001 3
05
06
07
18
19
1:
b00110 ;
b00110 <
b10110 E
b11110 F
b11001 I
b11001 J
1N
0S
1T
b00110 U
#350000
0N
#355000
b001110 *
b01110101000000000 +
0,
0-
b10000 .
b1000010011000011 /
b00010 2
b11001 3
15
16
17
b00110 E
b10110 F
b11110 G
1N
1S
#360000
0N
#365000
b001111 *
b10111010100000000 +
b01100 .
b1100001001100001 /
b01000 2
b00110 F
b10110 G
b11110 H
1N
#370000
0N
#375000
0'
b010000 *
b11011101010000000 +
b10010 .
b1110000100110000 /
10
b00101 2
04
05
06
07
b00001 ;
b00001 <
0>
b00110 G
b10110 H
b11110 I
b11110 J
1N
0S
b00001 U
#380000
0N
#385000
b11110 (
b010001 *
b01101110101000000 +
b11100 .
b1111000010011000 /
b10011 2
b11110 3
15
16
17
08
09
0:
b01000 ;
b01000 <
1>
b00001 E
b00110 H
b10110 I
b10110 J
1N
1S
0T
b01000 U
#390000
0N
#395000
b11100 (
b010010 *
b10110111010100000 +
b01010 .
b0111100001001100 /
00
01
b10000 2
b10110 3
18
19
1:
b11010 ;
b11010 <
b01000 E
b00001 F
b00110 I
b00110 J
1N
1T
b11010 U
#400000
0N
#405000
b11000 (
b010011 *
b11011011101010000 +
1,
1-
b11101 .
b1011110000100110 /
b00110 3
05
06
07
b10010 ;
b10011 <
b11010 E
b01000 F
b00001 G
b01010 J
b01100 K
1L
b00001 M
1N
0S
b10011 U
#410000
0N
#415000
1'
b10000 (
b010100 *
b01101101110101000 +
b10110 .
b1101111000010011 /
11
b11001 2
14
b11010 ;
b11011 <
b10011 E
b11010 F
b01000 G
b00001 H
1N
b11011 U
#420000
0N
#425000
b00001 (
b010101 *
b00110110111010100 +
b01111 .
b1110111100001001 /
10
01
b01100 2
15
16
17
b00000 ;
b00000 <
0>
b11011 E
b10011 F
b11010 G
b01000 H
b00001 I
b00001 J
b00000 K
0L
b00000 M
1N
1S
b00000 U
#430000
0N
#435000
0'
b00011 (
b010110 *
b10011011011101010 +
0,
0-
b01010 .
b1111011110000100 /
00
b11110 2
b00001 3
04
b00111 ;
b00110 <
1>
b00000 E
b11011 F
b10011 G
b11010 H
b01000 I
b00100 J
b01100 K
1L
b00001 M
1N
b00110 U
#440000
0N
#445000
1&
b00110 (
b010111 *
b11001101101110101 +
1-
b10101 .
b1111101111000010 /
b01000 3
14
b11100 ;
b11100 <
b00110 E
b00000 F
b11011 G
b10011 H
b11010 I
b11010 J
b00000 K
0L
b00000 M
1N
b11100 U
#450000
0N
#455000
0&
1'
b01101 (
b011000 *
b11100110110111010 +
0-
b11111 .
b1111110111100001 /
11
b10110 2
b11010 3
b11110 ;
b11110 <
b11100 E
b00110 F
b00000 G
b11011 H
b10011 I
b10011 J
1N
b11110 U
#460000
0N
#465000
1&
0'
b11011 (
b011001 *
b11110011011011101 +
1,
b11011 .
b1111111011110000 /
01
b11011 2
b10011 3
08
09
0:
b00000 ;
b00000 <
0>
b11110 E
b11100 F
b00110 G
b00000 H
b11011 I
b11011 J
1N
0T
b00000 U
#470000
0N
#475000
0&
b10111 (
b011010 *
b11111001101101110 +
1-
b10100 .
b0111111101111000 /
10
11
b11101 2
b11011 3
04
05
06
07
b11011 ;
b11010 <
1>
b00000 E
b11110 F
b11100 G
b00110 H
b00000 I
b01100 J
b01100 K
1L
b00001 M
1N
0S
b11010 U
#480000
0N
#485000
1&
b01110 (
b011011 *
b01111100110110111 +
0-
b10111 .
b0011111110111100 /
00
01
b11111 2
b00000 3
14
18
19
1:
b00100 ;
b00101 <
b11010 E
b00000 F
b11110 G
b11100 H
b00110 I
b01010 J
1N
1T
b00101 U
#490000
0N
#495000
b11101 (
b011100 *
b00111110011011011 +
b01011 .
b1001111111011110 /
b00110 3
15
16
17
08
09
0:
b00001 ;
b00001 <
0>
b00101 E
b11010 F
b00000 G
b11110 H
b11100 I
b11100 J
b00000 K
0L
b00000 M
1N
1S
0T
b00001 U
#500000
0N
#505000
1'
b11011 (
b011101 *
b10011111001101101 +
0,
1-
b01000 .
b0100111111101111 /
10
b01110 2
b11100 3
04
05
06
07
18
19
1:
b00101 ;
b00101 <
b00001 E
b00101 F
b11010 G
b00000 H
b11110 I
b11110 J
1N
0S
1T
b00101 U
#510000
0N
#515000
0&
b10110 (
b011110 *
b01001111100110110 +
1,
b11101 .
b1010011111110111 /
00
11
b01111 2
b11110 3
14
b10110 ;
b10110 <
1>
b00101 E
b00001 F
b00101 G
b11010 H
b00000 I
b00000 J
1N
b10110 U
#520000
0N
#525000
1&
b01101 (
b011111 *
b00100111110011011 +
0,
b01111 .
b1101001111111011 /
10
01
b11111 2
b00000 3
04
15
16
17
08
09
0:
b10111 ;
b10111 <
b10110 E
b00101 F
b00001 G
b00101 H
b11010 I
b11010 J
1N
1S
0T
b10111 U
#530000
0N
#535000
b11010 (
b100000 *
b10010011111001101 +
1,
0-
b01110 .
b0110100111111101 /
b00111 2
b11010 3
05
06
07
b11111 ;
b11111 <
b10111 E
b10110 F
b00101 G
b00001 H
b00101 I
b00101 J
1N
0S
b11111 U
#540000
0N
#545000
0&
0'
b10100 (
b100001 *
b01001001111100110 +
1-
b10110 .
b0011010011111110 /
11
b10011 2
b00101 3
15
16
17
18
19
1:
b10101 ;
b10101 <
0>
b11111 E
b10111 F
b10110 G
b00101 H
b00001 I
b00001 J
1N
1S
1T
b10101 U
#550000
0N
#555000
1&
1'
b01000 (
b100010 *
b10100100111110011 +
0-
b00111 .
b1001101001111111 /
00
b11001 2
b00001 3
05
06
07
b01101 ;
b01101 <
1>
b10101 E
b11111 F
b10111 G
b10110 H
b00101 I
b00101 J
1N
0S
b01101 U
#560000
0N
#565000
b10000 (
b100011 *
b01010010011111001 +
b11011 .
b1100110100111111 /
b00101 2
b00101 3
b00110 ;
b00110 <
b01101 E
b10101 F
b11111 G
b10111 H
b10110 I
b10110 J
1N
b00110 U
#570000
0N
#575000
0$
1%
0&
b00000 (
b001 )
b000000 *
b00101001001111100 +
0,
b00001 .
b1110011010011111 /
10
01
b01011 2
b10110 3
14
09
b10111 ;
b10111 <
0>
0C
1D
b00110 E
b01101 F
b10101 G
b11111 H
b10111 I
b10111 J
1N
b10111 U
#580000
0N
#585000
b00001 (
b000001 *
b00010100100111110 +
1,
1-
b00101 .
b1111001101001111 /
b11100 2
15
17
b10110 ;
b10110 <
1N
1S
b10110 U
#590000
0N
#595000
1&
b00011 (
b000010 *
b10001010010011111 +
0-
b01011 .
b1111100110100111 /
00
11
b10110 2
04
08
0:
b10100 ;
b10100 <
1N
0T
b10100 U
#600000
0N
#605000
b00110 (
b000011 *
b11000101001001111 +
b10000 .
b0111110011010011 /
b10011 2
b10001 ;
b10001 <
1N
b10001 U
#610000
0N
#615000
b01100 (
b000100 *
b11100010100100111 +
b11100 .
b0011111001101001 /
b11000 2
16
b11011 ;
b11011 <
1=
1C
1N
b11011 U
#620000
0N
#625000
0'
b11000 (
b000101 *
b11110001010010011 +
0,
1-
b10011 .
b0001111100110100 /
10
b11101 2
b10111 3
14
05
06
07
18
1:
b00111 ;
b00111 <
0=
b001 B
0C
b11011 E
b00110 F
b01101 G
b10101 H
b11111 I
b11111 J
1N
0S
1T
b00111 U
#630000
0N
#635000
b10001 (
b000110 *
b01111000101001001 +
b10100 .
b1000111110011010 /
b01111 2
b01110 ;
b01110 <
1N
b01110 U
#640000
0N
#645000
0&
1'
b00011 (
b000111 *
b00111100010100100 +
1,
b00010 .
b1100011111001101 /
01
b01110 2
15
17
b11100 ;
b11100 <
1N
1S
b11100 U
#650000
0N
#655000
0'
b00111 (
b001000 *
b10011110001010010 +
b01001 .
b1110001111100110 /
00
04
08
0:
b11000 ;
b11000 <
1N
0T
b11000 U
#660000
0N
#665000
1&
1'
b01110 (
b001001 *
b11001111000101001 +
0,
b11000 .
b0111000111110011 /
10
b10111 2
05
07
18
19
1:
b10001 ;
b10001 <
1=
1C
1N
0S
1T
b10001 U
#670000
0N
