rtl/WGT1_5.sv
// Fixed: Added logic type to output for consistency
module WGT1_5(input [4:0] address, output logic wgt1_5o);
   reg [31:0] LUT = 32'b00100111011110001010001101100101;
   assign wgt1_5o = LUT[address];
endmodule

rtl/mux2to1.sv
module mux2to1 (
  input logic sel,
  input logic a,
  input logic b,
  output logic y
);
  assign y = sel ? b : a;
endmodule

module bigmux2to1 (
  input logic sel,
  input logic [4:0] a,
  input logic [4:0] b,
  output logic [4:0] y
);
  assign y = sel ? b : a;
endmodule

rtl/gamma_mult.sv
`timescale 1ns/1ps
module gamma_mult(input [4:0] x, output [4:0] y);
  assign y[4] = x[1] ^ x[3] ^ x[4];
  assign y[3] = x[0] ^ x[1] ^ x[2];
  assign y[2] = x[0] ^ x[3] ^ x[4];
  assign y[1] = x[2] ^ x[3] ^ x[4];
  assign y[0] = x[2] ^ x[4];
endmodule

rtl/WGT2_5.sv
// Fixed: Added logic type to output for consistency
module WGT2_5(input [4:0] address, output logic wgt2_5o);
   reg [31:0] LUT = 32'b00000100000111111101110010011101;
   assign wgt2_5o = LUT[address];
endmodule

rtl/NLFSR3.sv
`timescale 1ns/1ps
module NLFSR3 (
  input  logic        clk,
  input  logic        rst,
  input  logic        load,
  input  logic        init,
  input  logic        nlfsr3_ce,
  input  logic [4:0]  d3,
  input  logic [4:0]  tk,
  output logic        o_warbler
);

  logic [4:0] next_C5;
  logic [4:0] C5, C4, C3, C2, C1, C0;
  logic [4:0] node1, node2, node3;
  logic [4:0] gamma_out;
  logic wgt2_5o;
  logic [4:0] pad_wgt2;

  // Fixed: Proper assignment instead of initialization
  assign pad_wgt2 = {4'b0000, wgt2_5o};

  assign node1 = gamma_out ^ C1;
  assign node2 = node1 ^ tk;
  assign node3 = node2 ^ pad_wgt2;

  // Fixed: Added port names for all instantiations
  WGT2_5 WGT2_5_inst (
    .address(C5),
    .wgt2_5o(wgt2_5o)
  );

  gamma_mult gamma_mult_inst (
    .x(pad_wgt2),
    .y(gamma_out)
  );

  bigmux2to1 bigmux2to1_inst (
    .sel(load),
    .a(node3),
    .b(d3),
    .y(next_C5)
  );

  WGT1_5 WGT1_5_inst (
    .address(C1),
    .wgt1_5o(o_warbler)
  );

  always_ff @(posedge clk or posedge rst) begin
    if (rst) begin
      C5 <= 5'b0;  // Fixed: Simplified reset values
      C4 <= 5'b0;
      C3 <= 5'b0;
      C2 <= 5'b0;
      C1 <= 5'b0;
      C0 <= 5'b0;
    end
    else if (nlfsr3_ce) begin
      C5 <= next_C5;
      C4 <= C5;
      C3 <= C4;
      C2 <= C3;
      C1 <= C2;
      C0 <= C1;
    end
  end
endmodule

rtl/shift5.sv
// input is xor a0 and b0
`timescale 1ns/1ps
module shift5 (
    input  logic        clk,
    input  logic        rst,
    input  logic        in_bit,
    output logic [4:0]  s
);
    always_ff @(posedge clk or posedge rst) begin
        if (rst)
            s <= 5'b0;
        else
            s <= {s[3:0], in_bit};
    end
endmodule

rtl/NLFSR2.sv
module NLFSR2 (
    input  logic        clk,
    input  logic        rst,
    input  logic        warbler_o,
    input  logic        nlfsr3_ce,
    input  logic        d2,
    input  logic        init,
    input  logic        load,
    output logic        b0
);
    logic [15:0] b;
    wire mux0_in, mux1_in;
    wire mux0_o, mux1_o, mux2_o;
    wire wgt1_5o;

    mux2to1 mux0 (nlfsr3_ce, 1'b0, mux0_in, mux0_o);
    mux2to1 mux1 (init,   mux1_in, mux0_o,  mux1_o);
    mux2to1 mux2 (load,   mux1_o,  d2,      mux2_o);
    WGT1_5 wlut    ({b[12], b[9], b[8], b[7], b[4]}, wgt1_5o);

    assign mux0_in = mux1_in ^ warbler_o;
    assign mux1_in = b[0] ^ wgt1_5o;
    assign b0      = b[0];

    // Shift-register logic
    always_ff @(posedge clk or posedge rst) begin
        if (rst)
            b <= '0;
        else
            b <= {mux2_o, b[15:1]};
    end
endmodule

rtl/NLFSR1.sv
`timescale 1ns/1ps
module NLFSR1 (
    input  logic        clk,
    input  logic        rst,
    input  logic        warbler_o,
    input  logic        nlfsr3_ce,
    input  logic        d1,
    input  logic        init,
    input  logic        load,
    output logic        a0
);
    logic [16:0] a;
    logic mux0_in, mux1_in;  // Fixed: Changed from wire to logic
    logic mux0_o, mux1_o, mux2_o;  // Fixed: Changed from wire to logic
    logic wgt1_5o;  // Fixed: Changed from wire to logic

    mux2to1 mux0 (.sel(nlfsr3_ce), .a(1'b0), .b(mux0_in), .y(mux0_o));  // Fixed: Added port names
    mux2to1 mux1 (.sel(init), .a(mux1_in), .b(mux0_o), .y(mux1_o));     // Fixed: Added port names
    mux2to1 mux2 (.sel(load), .a(mux1_o), .b(d1), .y(mux2_o));          // Fixed: Added port names
    WGT1_5 wlut (.address({a[15], a[10], a[8], a[7], a[4]}), .wgt1_5o(wgt1_5o));  // Fixed: Added port names

    assign mux0_in = mux1_in ^ warbler_o;
    assign mux1_in = a[0] ^ wgt1_5o;
    assign a0      = a[0];

    always_ff @(posedge clk or posedge rst) begin
        if (rst)
            a <= 17'b0;  // Fixed: Simplified reset value
        else
            a <= {mux2_o, a[16:1]};
    end
endmodule

rtl/fsm.sv
module fsm (
    input  logic clk,
    input  logic rst,
    output logic load_en,
    output logic init_en,
    output logic run_en,
    output logic nlfsr3_ce
);

    // State encoding (one-hot): LOAD=100, INIT=010, RUN=001
    localparam logic [2:0]
        LOAD = 3'b100,
        INIT = 3'b010,
        RUN  = 3'b001;

    logic [2:0] state;
    logic [5:0] cnt;

    // Sequential state and counter updates
    always_ff @(posedge clk or posedge rst) begin
        if (rst) begin
            state <= LOAD;
            cnt   <= 6'd0;
        end else begin
            case (state)
                LOAD: begin
                    if (cnt == 6'd17) begin    // 18 cycles for loading citeturn0file0
                        state <= INIT;
                        cnt   <= 6'd0;
                    end else begin
                        state <= LOAD;
                        cnt   <= cnt + 6'd1;
                    end
                end

                INIT: begin
                    if (cnt == 6'd35) begin    // 36 cycles for initialization citeturn0file0
                        state <= RUN;
                        cnt   <= 6'd0;
                    end else begin
                        state <= INIT;
                        cnt   <= cnt + 6'd1;
                    end
                end

                RUN: begin
                    state <= RUN;
                    cnt   <= cnt + 6'd1;       // free-running counter for mod-5 CE
                end

                default: begin
                    state <= LOAD;
                    cnt   <= 6'd0;
                end
            endcase
        end
    end

    // Output enables for each state
    assign load_en = (state == LOAD);
    assign init_en = (state == INIT);
    assign run_en  = (state == RUN);

    // NLFSR3 chip-enable: high during LOAD;
    // during INIT except first cycle; during RUN when cnt mod 5 == 4
    always_comb begin
        if (load_en) begin
            nlfsr3_ce = 1'b1;
        end else if (init_en) begin
            nlfsr3_ce = (cnt != 6'd0);
        end else begin
            nlfsr3_ce = (cnt % 6'd5 == 6'd4);
        end
    end

endmodule

rtl/trng.sv
module trng (
    input  logic        clk,
    input  logic        rst,
    input  logic        d1,
    input  logic        d2,
    input  logic [4:0]  d3,
    output logic        o_valid,
    output logic        o_warbler
);
    logic load_en, init_en, run_en, nlfsr3_ce;
    logic a0, b0;
    logic [4:0] s;
    logic warbler_bit; // Internal 1-bit signal for the output

    // FSM
    fsm fsm (.clk(clk), .rst(rst), .load_en(load_en), .init_en(init_en), .run_en(run_en), .nlfsr3_ce(nlfsr3_ce));
    
    // NLFSRs and shift register
    NLFSR1 nlfsr1 (.clk(clk), .rst(rst), .warbler_o(warbler_bit), .nlfsr3_ce(nlfsr3_ce), .d1(d1), .init(init_en), .load(load_en), .a0(a0));
    NLFSR2 nlfsr2 (.clk(clk), .rst(rst), .warbler_o(warbler_bit), .nlfsr3_ce(nlfsr3_ce), .d2(d2), .init(init_en), .load(load_en), .b0(b0));
    shift5 shift5 (.clk(clk), .rst(rst), .in_bit(a0 ^ b0), .s(s));
    NLFSR3 nlfsr3 (.clk(clk), .rst(rst), .load(load_en), .init(init_en), .nlfsr3_ce(nlfsr3_ce), .d3(d3), .tk(s), .o_warbler(warbler_bit));

    // Connect the internal warbler bit to the output
    assign o_warbler = warbler_bit;
    
    // valid output = NLFSR3 chip-enable
    assign o_valid = nlfsr3_ce;
endmodule

tests/test_trng/test_trng.sv
`timescale 1ns/1ps
module test_trng;
  // Common signals
  logic clk, rst;
  
  // Localparam for clock period
  localparam CLK_PERIOD = 10;
  
  // Clock generation
  always begin
    #(CLK_PERIOD/2) clk <= ~clk;
  end
  
  // Waveform generation
  initial begin
    $dumpfile("test_trng.vcd");
    $dumpvars(0, test_trng);
  end
  
  // =========== Top-level TRNG Test ===========
  logic trng_d1, trng_d2, trng_o_valid, trng_o_warbler;
  logic [4:0] trng_d3;
  
  trng trng_inst (
    .clk(clk),
    .rst(rst),
    .d1(trng_d1),
    .d2(trng_d2),
    .d3(trng_d3),
    .o_valid(trng_o_valid),
    .o_warbler(trng_o_warbler)
  );
  
  // Variables for TRNG test
  logic prev_warbler;
  logic changed;
  
  task automatic test_trng_basic_operation();
  // Declare variables at the beginning of the task
  integer warbler_o_high;
  integer warbler_o_low;
  integer diff;

  begin
    warbler_o_high = 0;
    warbler_o_low  = 0;
    diff = 0;

    trng_d1 = 1'b1;
    trng_d2 = 1'b0;
    trng_d3 = 5'b10101;

    // Reset should put FSM in LOAD state
    rst = 1'b1;
    #CLK_PERIOD;
    rst = 1'b0;
    repeat(200) @(posedge clk);

    // Check that o_valid is initially inactive
    assert(trng_o_valid == 1'b0) else
      $error("TRNG o_valid active after reset");

    // After 19 cycles (entering INIT state), o_valid should become active
    repeat(19) @(posedge clk);

    // Wait for transition to RUN state 
    repeat(36) @(posedge clk);

    // o_valid should be active every 5th cycle in RUN state
    @(posedge clk);
    for (int i = 1; i <= 10; i++) begin
      @(posedge clk);
      if (i % 5 == 0) begin
        assert(trng_o_valid == 1'b1) else
          $error("TRNG o_valid not active on 5th cycle during RUN state");
      end else begin
        assert(trng_o_valid == 1'b0) else
          $error("TRNG o_valid active on non-5th cycle during RUN state");
      end
    end

    // Run for 1000 more cycles and count high/low occurrences
    repeat(1000) begin
      @(posedge clk);
      if (trng_o_warbler == 1'b1 && trng_o_valid)
        warbler_o_high++;
      else if(trng_o_valid)
        warbler_o_low++;
    end

    diff = (warbler_o_high > warbler_o_low) ?
           (warbler_o_high - warbler_o_low) :
           (warbler_o_low - warbler_o_high);

    $display("TRNG o_warbler high: %0d, low: %0d, diff: %0d",
             warbler_o_high, warbler_o_low, diff);

    assert(diff <= 20) else
      $error("TRNG o_warbler output is skewed: imbalance of %0d exceeds threshold", diff);
  end
endtask

  
  // Main test sequence
  initial begin
    // Initialize signals
    clk = 0;
    rst = 1;
    
    // Release reset
    #(CLK_PERIOD * 2);
    rst = 0;
    #CLK_PERIOD;
    
    // Test TRNG top module
    $display("Testing TRNG top module...");
    test_trng_basic_operation();
    
    // Finish simulation
    #(CLK_PERIOD * 10);
    $display("TRNG test completed!");
    $finish();
  end

endmodule

tests/test_trng/test_trng.vcd
$version Generated by VerilatedVcd $end
$timescale 1ps $end
 $scope module $rootio $end
 $upscope $end
 $scope module test_trng $end
  $var wire 1 H clk $end
  $var wire 1 I rst $end
  $var wire 32 P CLK_PERIOD [31:0] $end
  $var wire 1 J trng_d1 $end
  $var wire 1 K trng_d2 $end
  $var wire 1 # trng_o_valid $end
  $var wire 1 $ trng_o_warbler $end
  $var wire 5 L trng_d3 [4:0] $end
  $var wire 1 Q prev_warbler $end
  $var wire 1 R changed $end
  $scope module trng_inst $end
   $var wire 1 H clk $end
   $var wire 1 I rst $end
   $var wire 1 J d1 $end
   $var wire 1 K d2 $end
   $var wire 5 L d3 [4:0] $end
   $var wire 1 # o_valid $end
   $var wire 1 $ o_warbler $end
   $var wire 1 % load_en $end
   $var wire 1 & init_en $end
   $var wire 1 ' run_en $end
   $var wire 1 # nlfsr3_ce $end
   $var wire 1 ( a0 $end
   $var wire 1 ) b0 $end
   $var wire 5 * s [4:0] $end
   $var wire 1 $ warbler_bit $end
   $scope module fsm $end
    $var wire 1 H clk $end
    $var wire 1 I rst $end
    $var wire 1 % load_en $end
    $var wire 1 & init_en $end
    $var wire 1 ' run_en $end
    $var wire 1 # nlfsr3_ce $end
    $var wire 3 S LOAD [2:0] $end
    $var wire 3 T INIT [2:0] $end
    $var wire 3 U RUN [2:0] $end
    $var wire 3 + state [2:0] $end
    $var wire 6 , cnt [5:0] $end
   $upscope $end
   $scope module nlfsr1 $end
    $var wire 1 H clk $end
    $var wire 1 I rst $end
    $var wire 1 $ warbler_o $end
    $var wire 1 # nlfsr3_ce $end
    $var wire 1 J d1 $end
    $var wire 1 & init $end
    $var wire 1 % load $end
    $var wire 1 ( a0 $end
    $var wire 17 - a [16:0] $end
    $var wire 1 . mux0_in $end
    $var wire 1 / mux1_in $end
    $var wire 1 0 mux0_o $end
    $var wire 1 1 mux1_o $end
    $var wire 1 M mux2_o $end
    $var wire 1 2 wgt1_5o $end
    $scope module mux0 $end
     $var wire 1 # sel $end
     $var wire 1 V a $end
     $var wire 1 . b $end
     $var wire 1 0 y $end
    $upscope $end
    $scope module mux1 $end
     $var wire 1 & sel $end
     $var wire 1 / a $end
     $var wire 1 0 b $end
     $var wire 1 1 y $end
    $upscope $end
    $scope module mux2 $end
     $var wire 1 % sel $end
     $var wire 1 1 a $end
     $var wire 1 J b $end
     $var wire 1 M y $end
    $upscope $end
    $scope module wlut $end
     $var wire 5 3 address [4:0] $end
     $var wire 1 2 wgt1_5o $end
     $var wire 32 W LUT [31:0] $end
    $upscope $end
   $upscope $end
   $scope module nlfsr2 $end
    $var wire 1 H clk $end
    $var wire 1 I rst $end
    $var wire 1 $ warbler_o $end
    $var wire 1 # nlfsr3_ce $end
    $var wire 1 K d2 $end
    $var wire 1 & init $end
    $var wire 1 % load $end
    $var wire 1 ) b0 $end
    $var wire 16 4 b [15:0] $end
    $var wire 1 5 mux0_in $end
    $var wire 1 6 mux1_in $end
    $var wire 1 7 mux0_o $end
    $var wire 1 8 mux1_o $end
    $var wire 1 N mux2_o $end
    $var wire 1 9 wgt1_5o $end
    $scope module mux0 $end
     $var wire 1 # sel $end
     $var wire 1 V a $end
     $var wire 1 5 b $end
     $var wire 1 7 y $end
    $upscope $end
    $scope module mux1 $end
     $var wire 1 & sel $end
     $var wire 1 6 a $end
     $var wire 1 7 b $end
     $var wire 1 8 y $end
    $upscope $end
    $scope module mux2 $end
     $var wire 1 % sel $end
     $var wire 1 8 a $end
     $var wire 1 K b $end
     $var wire 1 N y $end
    $upscope $end
    $scope module wlut $end
     $var wire 5 : address [4:0] $end
     $var wire 1 9 wgt1_5o $end
     $var wire 32 W LUT [31:0] $end
    $upscope $end
   $upscope $end
   $scope module nlfsr3 $end
    $var wire 1 H clk $end
    $var wire 1 I rst $end
    $var wire 1 % load $end
    $var wire 1 & init $end
    $var wire 1 # nlfsr3_ce $end
    $var wire 5 L d3 [4:0] $end
    $var wire 5 * tk [4:0] $end
    $var wire 1 $ o_warbler $end
    $var wire 5 O next_C5 [4:0] $end
    $var wire 5 ; C5 [4:0] $end
    $var wire 5 < C4 [4:0] $end
    $var wire 5 = C3 [4:0] $end
    $var wire 5 > C2 [4:0] $end
    $var wire 5 ? C1 [4:0] $end
    $var wire 5 @ C0 [4:0] $end
    $var wire 5 A node1 [4:0] $end
    $var wire 5 B node2 [4:0] $end
    $var wire 5 C node3 [4:0] $end
    $var wire 5 D gamma_out [4:0] $end
    $var wire 1 E wgt2_5o $end
    $var wire 5 F pad_wgt2 [4:0] $end
    $scope module WGT1_5_inst $end
     $var wire 5 ? address [4:0] $end
     $var wire 1 $ wgt1_5o $end
     $var wire 32 W LUT [31:0] $end
    $upscope $end
    $scope module WGT2_5_inst $end
     $var wire 5 ; address [4:0] $end
     $var wire 1 E wgt2_5o $end
     $var wire 32 X LUT [31:0] $end
    $upscope $end
    $scope module bigmux2to1_inst $end
     $var wire 1 % sel $end
     $var wire 5 C a [4:0] $end
     $var wire 5 L b [4:0] $end
     $var wire 5 O y [4:0] $end
    $upscope $end
    $scope module gamma_mult_inst $end
     $var wire 5 F x [4:0] $end
     $var wire 5 D y [4:0] $end
    $upscope $end
   $upscope $end
   $scope module shift5 $end
    $var wire 1 H clk $end
    $var wire 1 I rst $end
    $var wire 1 G in_bit $end
    $var wire 5 * s [4:0] $end
   $upscope $end
  $upscope $end
 $upscope $end
$enddefinitions $end


#0
0#
1$
0%
0&
0'
0(
0)
b00000 *
b000 +
b000000 ,
b00000000000000000 -
0.
1/
00
11
12
b00000 3
b0000000000000000 4
05
16
07
18
19
b00000 :
b00000 ;
b00000 <
b00000 =
b00000 >
b00000 ?
b00000 @
b01100 A
b01100 B
b01101 C
b01100 D
1E
b00001 F
0G
0H
1I
0J
0K
b00000 L
1M
1N
b01101 O
b00000000000000000000000000001010 P
0Q
0R
b100 S
b010 T
b001 U
0V
b00100111011110001010001101100101 W
b00000100000111111101110010011101 X
#5000
1#
1%
b100 +
1H
0M
0N
b00000 O
#10000
0H
#15000
1H
#20000
0H
0I
#25000
b000001 ,
1H
#30000
b000000 ,
0H
1I
1J
b10101 L
1M
b10101 O
#35000
1H
#40000
0H
0I
#45000
b000001 ,
b10000000000000000 -
b10101 ;
b00000 A
b00000 B
b00000 C
b00000 D
0E
b00000 F
1H
#50000
0H
#55000
b000010 ,
b11000000000000000 -
1.
0/
10
01
02
b10000 3
b10101 <
1H
#60000
0H
#65000
b000011 ,
b11100000000000000 -
b10101 =
1H
#70000
0H
#75000
b000100 ,
b11110000000000000 -
b10101 >
1H
#80000
0H
#85000
b000101 ,
b11111000000000000 -
b10101 ?
b10101 A
b10101 B
b10101 C
1H
#90000
0H
#95000
b000110 ,
b11111100000000000 -
b10101 @
1H
#100000
0H
#105000
b000111 ,
b11111110000000000 -
0.
1/
00
11
12
b11000 3
1H
#110000
0H
#115000
b001000 ,
b11111111000000000 -
1H
#120000
0H
#125000
b001001 ,
b11111111100000000 -
1.
0/
10
01
02
b11100 3
1H
#130000
0H
#135000
b001010 ,
b11111111110000000 -
b11110 3
1H
#140000
0H
#145000
b001011 ,
b11111111111000000 -
1H
#150000
0H
#155000
b001100 ,
b11111111111100000 -
1H
#160000
0H
#165000
b001101 ,
b11111111111110000 -
b11111 3
1H
#170000
0H
#175000
b001110 ,
b11111111111111000 -
1H
#180000
0H
#185000
b001111 ,
b11111111111111100 -
1H
#190000
0H
#195000
b010000 ,
b11111111111111110 -
1H
#200000
0H
#205000
1(
b010001 ,
b11111111111111111 -
0.
1/
00
11
1G
1H
#210000
0H
#215000
0#
0%
1&
b00001 *
b010 +
b000000 ,
01
08
b10100 B
b10100 C
1H
0M
b10100 O
#220000
0H
#225000
1#
b00011 *
b000001 ,
b01111111111111111 -
b10110 B
b10110 C
1H
b10110 O
#230000
0H
#235000
b00111 *
b000010 ,
b00111111111111111 -
1.
0/
10
11
12
b01111 3
b10110 ;
b10010 B
b10010 C
1H
1M
b10010 O
#240000
0H
#245000
b01111 *
b000011 ,
b10011111111111111 -
b10010 ;
b10110 <
b11001 A
b10110 B
b10111 C
b01100 D
1E
b00001 F
1H
b10111 O
#250000
0H
#255000
b11111 *
b000100 ,
b11001111111111111 -
0.
1/
00
01
02
b11111 3
b10111 ;
b10010 <
b10110 =
b10101 A
b01010 B
b01010 C
b00000 D
0E
b00000 F
1H
0M
b01010 O
#260000
0H
#265000
b000101 ,
b01100111111111111 -
b01010 ;
b10111 <
b10010 =
b10110 >
b11001 A
b00110 B
b00111 C
b01100 D
1E
b00001 F
1H
b00111 O
#270000
0H
#275000
b000110 ,
b00110011111111111 -
1.
0/
10
11
12
b01111 3
b00111 ;
b01010 <
b10111 =
b10010 >
b10110 ?
b11010 A
b00101 B
b00100 C
1H
1M
b00100 O
#280000
0H
#285000
0$
b000111 ,
b10011001111111111 -
1/
02
b00111 3
15
17
18
b00100 ;
b00111 <
b01010 =
b10111 >
b10010 ?
b10110 @
b11110 A
b00001 B
b00000 C
1H
1N
b00000 O
#290000
0H
#295000
b001000 ,
b11001100111111111 -
b10111 3
b1000000000000000 4
b00000 ;
b00100 <
b00111 =
b01010 >
b10111 ?
b10010 @
b11011 A
b00100 B
b00101 C
1H
b00101 O
#300000
0H
#305000
b001001 ,
b11100110011111111 -
b11011 3
b1100000000000000 4
b00101 ;
b00000 <
b00100 =
b00111 >
b01010 ?
b10111 @
b01010 A
b10101 B
b10101 C
b00000 D
0E
b00000 F
1H
b10101 O
#310000
0H
#315000
b001010 ,
b11110011001111111 -
0.
0/
00
01
12
b11001 3
b1110000000000000 4
b10101 ;
b00101 <
b00000 =
b00100 >
b00111 ?
b01010 @
b00111 A
b11000 B
b11000 C
1H
0M
b11000 O
#320000
0H
#325000
b001011 ,
b01111001100111111 -
b10101 3
b1111000000000000 4
05
06
07
08
09
b10000 :
b11000 ;
b10101 <
b00101 =
b00000 >
b00100 ?
b00111 @
b00100 A
b11011 B
b11011 C
1H
0N
b11011 O
#330000
0H
#335000
1$
b001100 ,
b00111100110011111 -
1/
02
b00111 3
b0111100000000000 4
15
17
18
b11011 ;
b11000 <
b10101 =
b00101 >
b00000 ?
b00100 @
b00000 A
b11111 B
b11111 C
1H
1N
b11111 O
#340000
0H
#345000
b001101 ,
b00011110011001111 -
b01010 3
b1011110000000000 4
b11111 ;
b11011 <
b11000 =
b10101 >
b00101 ?
b00000 @
b00101 A
b11010 B
b11010 C
1H
b11010 O
#350000
0H
#355000
b001110 ,
b00001111001100111 -
1.
0/
10
11
12
b01000 3
b1101111000000000 4
05
16
07
08
19
b11000 :
b11010 ;
b11111 <
b11011 =
b11000 >
b10101 ?
b00101 @
b11001 A
b00110 B
b00111 C
b01100 D
1E
b00001 F
1H
1M
0N
b00111 O
#360000
0H
#365000
b001111 ,
b10000111100110011 -
b01101 3
b0110111100000000 4
15
06
17
18
09
b01100 :
b00111 ;
b11010 <
b11111 =
b11011 >
b11000 ?
b10101 @
b10100 A
b01011 B
b01010 C
1H
1N
b01010 O
#370000
0H
#375000
0$
b010000 ,
b11000011110011001 -
1/
02
b11111 3
b1011011110000000 4
05
07
08
b11110 :
b01010 ;
b00111 <
b11010 =
b11111 >
b11011 ?
b11000 @
b10111 A
b01000 B
b01001 C
1H
0N
b01001 O
#380000
0H
#385000
0(
b010001 ,
b11100001111001100 -
12
b10110 3
b0101101111000000 4
b01001 ;
b01010 <
b00111 =
b11010 >
b11111 ?
b11011 @
b11111 A
b00000 B
b00000 C
b00000 D
0E
b00000 F
0G
1H
b00000 O
#390000
0H
#395000
1$
b11110 *
b010010 ,
b11110000111100110 -
0.
00
01
b0010110111100000 4
16
19
b00110 :
b00000 ;
b01001 <
b01010 =
b00111 >
b11010 ?
b11111 @
b10110 A
b01000 B
b01001 C
b01100 D
1E
b00001 F
1H
0M
b01001 O
#400000
0H
#405000
0$
1(
b11100 *
b010011 ,
b01111000011110011 -
0/
b10011 3
b0001011011110000 4
06
09
b11011 :
b01001 ;
b00000 <
b01001 =
b01010 >
b00111 ?
b11010 @
b00111 A
b11011 B
b11011 C
b00000 D
0E
b00000 F
1G
1H
b11011 O
#410000
0H
#415000
b11001 *
b010100 ,
b00111100001111001 -
1.
1/
10
11
02
b00001 3
b0000101101111000 4
15
16
17
18
19
b01101 :
b11011 ;
b01001 <
b00000 =
b01001 >
b01010 ?
b00111 @
b01010 A
b10011 B
b10011 C
1H
1M
1N
b10011 O
#420000
0H
#425000
1$
0(
b10011 *
b010101 ,
b10011110000111100 -
0.
00
01
12
b01001 3
b1000010110111100 4
06
09
b00111 :
b10011 ;
b11011 <
b01001 =
b00000 >
b01001 ?
b01010 @
b00101 A
b10110 B
b10111 C
b01100 D
1E
b00001 F
0G
1H
0M
b10111 O
#430000
0H
#435000
b00110 *
b010110 ,
b01001111000011110 -
b11001 3
b1100001011011110 4
b01011 :
b10111 ;
b10011 <
b11011 =
b01001 >
b00000 ?
b01001 @
b00000 A
b00110 B
b00110 C
b00000 D
0E
b00000 F
1H
b00110 O
#440000
0H
#445000
1(
1)
b01100 *
b010111 ,
b00100111100001111 -
02
b01100 3
b1110000101101111 4
05
16
07
08
b00100 :
b00110 ;
b10111 <
b10011 =
b11011 >
b01001 ?
b00000 @
b01001 A
b00101 B
b00101 C
1H
0N
b00101 O
#450000
0H
#455000
0$
b11000 *
b011000 ,
b00010011110000111 -
1.
10
11
b01110 3
b0111000010110111 4
06
19
b10011 :
b00101 ;
b00110 <
b10111 =
b10011 >
b11011 ?
b01001 @
b11011 A
b00011 B
b00011 C
1H
1M
b00011 O
#460000
0H
#465000
1$
b10000 *
b011001 ,
b10001001111000011 -
0/
12
b00110 3
b0011100001011011 4
16
09
b10001 :
b00011 ;
b00101 <
b00110 =
b10111 >
b10011 ?
b11011 @
b11111 A
b01111 B
b01110 C
b01100 D
1E
b00001 F
1H
b01110 O
#470000
0H
#475000
0$
b00000 *
b011010 ,
b11000100111100001 -
0.
00
01
b10110 3
b0001110000101101 4
15
17
18
b10000 :
b01110 ;
b00011 <
b00101 =
b00110 >
b10111 ?
b10011 @
b11011 A
b11011 B
b11010 C
1H
0M
1N
b11010 O
#480000
0H
#485000
1$
0(
0)
b011011 ,
b01100010011110000 -
1.
10
11
02
b11011 3
b1000111000010110 4
05
07
08
19
b01001 :
b11010 ;
b01110 <
b00011 =
b00101 >
b00110 ?
b10111 @
b01010 A
b01010 B
b01011 C
1H
1M
0N
b01011 O
#490000
0H
#495000
1)
b011100 ,
b10110001001111000 -
b00001 3
b0100011100001011 4
09
b01100 :
b01011 ;
b11010 <
b01110 =
b00011 >
b00101 ?
b00110 @
b01001 A
b01001 B
b01000 C
1G
1H
b01000 O
#500000
0H
#505000
0$
b00001 *
b011101 ,
b11011000100111100 -
1/
12
b10101 3
b0010001110000101 4
15
17
18
b01110 :
b01000 ;
b01011 <
b11010 =
b01110 >
b00011 ?
b00101 @
b00011 A
b00010 B
b00010 C
b00000 D
0E
b00000 F
1H
1N
b00010 O
#510000
0H
#515000
0)
b00011 *
b011110 ,
b11101100010011110 -
b10011 3
b1001000111000010 4
19
b10110 :
b00010 ;
b01000 <
b01011 =
b11010 >
b01110 ?
b00011 @
b00010 A
b00001 B
b00000 C
b01100 D
1E
b00001 F
0G
1H
b00000 O
#520000
0H
#525000
1$
1(
1)
b00110 *
b011111 ,
b11110110001001111 -
0/
b11000 3
b1100100011100001 4
06
b00010 :
b00000 ;
b00010 <
b01000 =
b01011 >
b11010 ?
b01110 @
b10110 A
b10000 B
b10001 C
1H
b10001 O
#530000
0H
#535000
0$
0)
b01100 *
b100000 ,
b11111011000100111 -
0.
00
01
b1110010001110000 4
05
07
08
09
b00001 :
b10001 ;
b00000 <
b00010 =
b01000 >
b01011 ?
b11010 @
b00111 A
b01011 B
b01010 C
1G
1H
0M
0N
b01010 O
#540000
0H
#545000
1$
b11001 *
b100001 ,
b01111101100010011 -
1.
10
11
b10101 3
b0111001000111000 4
16
19
b11001 :
b01010 ;
b10001 <
b00000 =
b00010 >
b01000 ?
b01011 @
b00100 A
b11101 B
b11100 C
1H
1M
b11100 O
#550000
0H
#555000
b10011 *
b100010 ,
b10111110110001001 -
0.
1/
00
01
02
b01110 3
b0011100100011100 4
b10101 :
b11100 ;
b01010 <
b10001 =
b00000 >
b00010 ?
b01000 @
b00010 A
b10001 B
b10001 C
b00000 D
0E
b00000 F
1H
0M
b10001 O
#560000
0H
#565000
0(
b00111 *
b100011 ,
b01011111011000100 -
12
b11010 3
b0001110010001110 4
15
06
17
18
09
b10010 :
b10001 ;
b11100 <
b01010 =
b10001 >
b00000 ?
b00010 @
b01100 A
b01011 B
b01010 C
b01100 D
1E
b00001 F
0G
1H
1N
b01010 O
#570000
0H
#575000
0#
0$
0&
1'
1)
b01110 *
b001 +
b000000 ,
b00101111101100010 -
0/
02
b01100 3
b1000111001000111 4
05
07
08
19
b01000 :
b01010 ;
b10001 <
b11100 =
b01010 >
b10001 ?
b00000 @
b11101 A
b10011 B
b10010 C
1G
1H
0N
b10010 O
#580000
0H
#585000
1(
b11101 *
b000001 ,
b00010111110110001 -
12
b01111 3
b0100011100100011 4
15
16
18
09
b01100 :
b00000 B
b00001 C
0G
1H
1N
b00001 O
#590000
0H
#595000
0(
b11010 *
b000010 ,
b00001011111011000 -
1.
1/
11
b1010001110010001 4
05
06
08
19
b01111 :
b00111 B
b00110 C
1G
1H
1M
0N
b00110 O
#600000
0H
#605000
0)
b10101 *
b000011 ,
b10000101111101100 -
b00110 3
b0101000111001000 4
15
16
18
b10110 :
b01000 B
b01001 C
0G
1H
1N
b01001 O
#610000
0H
#615000
1#
b01010 *
b000100 ,
b11000010111110110 -
0.
0/
01
02
b11111 3
b1010100011100100 4
17
b00010 :
b10111 B
b10110 C
1H
0M
b10110 O
#620000
0H
#625000
0#
1(
b10100 *
b000101 ,
b01100001011111011 -
12
b10011 3
b1101010001110010 4
05
06
07
08
09
b10001 :
b10110 ;
b01010 <
b10001 =
b11100 >
b01010 ?
b10001 @
b01010 A
b11110 B
b11110 C
b00000 D
0E
b00000 F
1G
1H
0N
b11110 O
#630000
0H
#635000
1)
b01001 *
b000110 ,
b00110000101111101 -
b00101 3
b0110101000111001 4
19
b01001 :
b00011 B
b00011 C
0G
1H
b00011 O
#640000
0H
#645000
0(
0)
b10010 *
b000111 ,
b00011000010111110 -
02
b00011 3
b0011010100011100 4
15
16
18
b10101 :
b11000 B
b11000 C
1H
1N
b11000 O
#650000
0H
#655000
1(
b00100 *
b001000 ,
b00001100001011111 -
1.
1/
11
b00001 3
b1001101010001110 4
b11010 :
b01110 B
b01110 C
1G
1H
1M
b01110 O
#660000
0H
#665000
1#
1)
b01001 *
b001001 ,
b10000110000101111 -
0.
0/
01
12
b01000 3
b1100110101000111 4
17
09
b00100 :
b00011 B
b00011 C
0G
1H
0M
b00011 O
#670000
0H
