rtl/fsm.sv
module fsm (
    input  logic clk,
    input  logic rst,
    output logic load_en,
    output logic init_en,
    output logic run_en,
    output logic nlfsr3_ce,
    output logic output_en
);

    // State encoding (one-hot): LOAD=100, INIT=010, RUN=001
    localparam logic [2:0]
        LOAD = 3'b100,
        INIT = 3'b010,
        RUN  = 3'b001;

    logic [2:0] state;
    logic [5:0] cnt;

    // Sequential state and counter updates
    always_ff @(posedge clk or posedge rst) begin
        if (rst) begin
            state <= LOAD;
            cnt   <= 6'd0;
        end else begin
            case (state)
                LOAD: begin
                    if (cnt == 6'd17) begin    // 18 cycles for loading citeturn0file0
                        state <= INIT;
                        cnt   <= 6'd0;
                    end else begin
                        state <= LOAD;
                        cnt   <= cnt + 6'd1;
                    end
                end

                INIT: begin
                    if (cnt == 6'd35) begin    // 36 cycles for initialization citeturn0file0
                        state <= RUN;
                        cnt   <= 6'd0;
                    end else begin
                        state <= INIT;
                        cnt   <= cnt + 6'd1;
                    end
                end

                RUN: begin
                    state <= RUN;
                    cnt   <= cnt + 6'd1;       // free-running counter for mod-5 CE
                end

                default: begin
                    state <= LOAD;
                    cnt   <= 6'd0;
                end
            endcase
        end
    end

    // Output enables for each state
    assign load_en = (state == LOAD);
    assign init_en = (state == INIT);
    assign run_en  = (state == RUN);

    // NLFSR3 chip-enable: high during LOAD;
    // during INIT except first cycle; during RUN when cnt mod 5 == 4
    always_comb begin
        if (load_en) begin
            nlfsr3_ce = 1'b1;
            output_en = 1'b0;
        end else if (init_en) begin
            output_en = 1'b0;
            nlfsr3_ce = (cnt != 6'd0);
        end else begin
            nlfsr3_ce = (cnt % 6'd5 == 6'd4);
            output_en = 1'b1;
        end
    end

endmodule

tests/test_fsm/test_fsm.sv
`timescale 1ns/1ps
module test_fsm;
  // Common signals
  logic clk, rst;
  
  // Localparam for clock period
  localparam CLK_PERIOD = 10;
  
  // Clock generation
  always begin
    #(CLK_PERIOD/2) clk <= ~clk;
  end
  
  // Waveform generation
  initial begin
    $dumpfile("test_aesfsm.vcd");
    $dumpvars(0, test_fsm);
  end
  
  // =========== FSM Test ===========
  logic fsm_load_en, fsm_init_en, fsm_run_en, fsm_nlfsr3_ce;
  
  fsm fsm_inst (
    .clk(clk),
    .rst(rst),
    .load_en(fsm_load_en),
    .init_en(fsm_init_en),
    .run_en(fsm_run_en),
    .nlfsr3_ce(fsm_nlfsr3_ce)
  );
  
  task automatic test_fsm_states();
    begin
      // Test LOAD state
      assert(fsm_load_en == 1'b1 && fsm_init_en == 1'b0 && fsm_run_en == 1'b0) else
        $error("FSM not in correct LOAD state at startup");
      
      // Wait for transition to INIT (after 17 cycles)
      repeat(17) @(posedge clk);
      
      assert(fsm_load_en == 1'b0 && fsm_init_en == 1'b1 && fsm_run_en == 1'b0) else
        $error("FSM did not transition to INIT state after 17 cycles");
      
      // Wait for transition to RUN (after additional 36 cycles)
      repeat(36) @(posedge clk);
      
      assert(fsm_load_en == 1'b0 && fsm_init_en == 1'b0 && fsm_run_en == 1'b1) else
        $error("FSM did not transition to RUN state after 36 more cycles");
      
      // Test nlfsr3_ce signal in RUN state (should be active every 5th cycle)
      @(posedge clk);
      for (int i = 1; i <= 10; i++) begin
        @(posedge clk);
        if (i % 5 == 0) begin
          assert(fsm_nlfsr3_ce == 1'b1) else
            $error("FSM nlfsr3_ce not active on 5th cycle during RUN state");
        end else begin
          assert(fsm_nlfsr3_ce == 1'b0) else
            $error("FSM nlfsr3_ce active on non-5th cycle during RUN state");
        end
      end
    end
  endtask
  
  // Main test sequence
  initial begin
    // Initialize signals
    clk = 0;
    rst = 1;
    
    // Release reset
    #(CLK_PERIOD * 2);
    rst = 0;
    #CLK_PERIOD;
    
    // Test FSM
    $display("Testing FSM module...");
    test_fsm_states();
    
    // Finish simulation
    #(CLK_PERIOD * 10);
    $display("FSM test completed!");
    $finish();
  end

endmodule

tests/test_fsm/test_aesfsm.vcd
$date
	Sat Jun  7 23:59:32 2025
$end
$version
	Icarus Verilog
$end
$timescale
	1ps
$end
$scope module test_fsm $end
$var wire 1 ! fsm_run_en $end
$var wire 1 " fsm_nlfsr3_ce $end
$var wire 1 # fsm_load_en $end
$var wire 1 $ fsm_init_en $end
$var parameter 32 % CLK_PERIOD $end
$var reg 1 & clk $end
$var reg 1 ' rst $end
$scope module fsm_inst $end
$var wire 1 & clk $end
$var wire 1 ' rst $end
$var wire 1 ! run_en $end
$var wire 1 # load_en $end
$var wire 1 $ init_en $end
$var parameter 3 ( INIT $end
$var parameter 3 ) LOAD $end
$var parameter 3 * RUN $end
$var reg 6 + cnt [5:0] $end
$var reg 1 " nlfsr3_ce $end
$var reg 1 , output_en $end
$var reg 3 - state [2:0] $end
$upscope $end
$scope task test_fsm_states $end
$scope begin $ivl_for_loop0 $end
$upscope $end
$upscope $end
$upscope $end
$enddefinitions $end
$comment Show the parameter values. $end
$dumpall
b1 *
b100 )
b10 (
b1010 %
$end
#0
$dumpvars
b100 -
0,
b0 +
1'
0&
0$
1#
1"
0!
$end
#5000
1&
#10000
0&
#15000
1&
#20000
0&
0'
#25000
b1 +
1&
#30000
0&
#35000
b10 +
1&
#40000
0&
#45000
b11 +
1&
#50000
0&
#55000
b100 +
1&
#60000
0&
#65000
b101 +
1&
#70000
0&
#75000
b110 +
1&
#80000
0&
#85000
b111 +
1&
#90000
0&
#95000
b1000 +
1&
#100000
0&
#105000
b1001 +
1&
#110000
0&
#115000
b1010 +
1&
#120000
0&
#125000
b1011 +
1&
#130000
0&
#135000
b1100 +
1&
#140000
0&
#145000
b1101 +
1&
#150000
0&
#155000
b1110 +
1&
#160000
0&
#165000
b1111 +
1&
#170000
0&
#175000
b10000 +
1&
#180000
0&
#185000
b10001 +
1&
#190000
0&
#195000
0"
b0 +
0#
1$
b10 -
1&
#200000
0&
#205000
1"
b1 +
1&
#210000
0&
#215000
b10 +
1&
#220000
0&
#225000
b11 +
1&
#230000
0&
#235000
b100 +
1&
#240000
0&
#245000
b101 +
1&
#250000
0&
#255000
b110 +
1&
#260000
0&
#265000
b111 +
1&
#270000
0&
#275000
b1000 +
1&
#280000
0&
#285000
b1001 +
1&
#290000
0&
#295000
b1010 +
1&
#300000
0&
#305000
b1011 +
1&
#310000
0&
#315000
b1100 +
1&
#320000
0&
#325000
b1101 +
1&
#330000
0&
#335000
b1110 +
1&
#340000
0&
#345000
b1111 +
1&
#350000
0&
#355000
b10000 +
1&
#360000
0&
#365000
b10001 +
1&
#370000
0&
#375000
b10010 +
1&
#380000
0&
#385000
b10011 +
1&
#390000
0&
#395000
b10100 +
1&
#400000
0&
#405000
b10101 +
1&
#410000
0&
#415000
b10110 +
1&
#420000
0&
#425000
b10111 +
1&
#430000
0&
#435000
b11000 +
1&
#440000
0&
#445000
b11001 +
1&
#450000
0&
#455000
b11010 +
1&
#460000
0&
#465000
b11011 +
1&
#470000
0&
#475000
b11100 +
1&
#480000
0&
#485000
b11101 +
1&
#490000
0&
#495000
b11110 +
1&
#500000
0&
#505000
b11111 +
1&
#510000
0&
#515000
b100000 +
1&
#520000
0&
#525000
b100001 +
1&
#530000
0&
#535000
b100010 +
1&
#540000
0&
#545000
b100011 +
1&
#550000
0&
#555000
1,
0"
b0 +
0$
1!
b1 -
1&
#560000
0&
#565000
b1 +
1&
#570000
0&
#575000
b10 +
1&
#580000
0&
#585000
b11 +
1&
#590000
0&
#595000
1"
b100 +
1&
#600000
0&
#605000
0"
b101 +
1&
#610000
0&
#615000
b110 +
1&
#620000
0&
#625000
b111 +
1&
#630000
0&
#635000
b1000 +
1&
#640000
0&
#645000
1"
b1001 +
1&
#650000
0&
#655000
0"
b1010 +
1&
#660000
0&
#665000
b1011 +
1&
#670000
0&
#675000
b1100 +
1&
#680000
0&
#685000
b1101 +
1&
#690000
0&
#695000
1"
b1110 +
1&
#700000
0&
#705000
0"
b1111 +
1&
#710000
0&
#715000
b10000 +
1&
#720000
0&
#725000
b10001 +
1&
#730000
0&
#735000
b10010 +
1&
#740000
0&
#745000
1"
b10011 +
1&
#750000
0&
#755000
0"
b10100 +
1&
#760000
0&
#765000
b10101 +
1&
