rtl/fsm.sv
module fsm (
    input  logic clk,
    input  logic rst,
    output logic load_en,
    output logic init_en,
    output logic run_en,
    output logic nlfsr3_ce
);

    // State encoding (one-hot): LOAD=100, INIT=010, RUN=001
    localparam logic [2:0]
        LOAD = 3'b100,
        INIT = 3'b010,
        RUN  = 3'b001;

    logic [2:0] state;
    logic [5:0] cnt;

    // Sequential state and counter updates
    always_ff @(posedge clk or posedge rst) begin
        if (rst) begin
            state <= LOAD;
            cnt   <= 6'd0;
        end else begin
            case (state)
                LOAD: begin
                    if (cnt == 6'd17) begin    // 18 cycles for loading citeturn0file0
                        state <= INIT;
                        cnt   <= 6'd0;
                    end else begin
                        state <= LOAD;
                        cnt   <= cnt + 6'd1;
                    end
                end

                INIT: begin
                    if (cnt == 6'd35) begin    // 36 cycles for initialization citeturn0file0
                        state <= RUN;
                        cnt   <= 6'd0;
                    end else begin
                        state <= INIT;
                        cnt   <= cnt + 6'd1;
                    end
                end

                RUN: begin
                    state <= RUN;
                    cnt   <= cnt + 6'd1;       // free-running counter for mod-5 CE
                end

                default: begin
                    state <= LOAD;
                    cnt   <= 6'd0;
                end
            endcase
        end
    end

    // Output enables for each state
    assign load_en = (state == LOAD);
    assign init_en = (state == INIT);
    assign run_en  = (state == RUN);

    // NLFSR3 chip-enable: high during LOAD;
    // during INIT except first cycle; during RUN when cnt mod 5 == 4
    always_comb begin
        if (load_en) begin
            nlfsr3_ce = 1'b1;
        end else if (init_en) begin
            nlfsr3_ce = (cnt != 6'd0);
        end else begin
            nlfsr3_ce = (cnt % 6'd5 == 6'd4);
        end
    end

endmodule

tests/test_fsm/test_fsm.sv
`timescale 1ns/1ps
module test_fsm;
  // Common signals
  logic clk, rst;
  
  // Localparam for clock period
  localparam CLK_PERIOD = 10;
  
  // Clock generation
  always begin
    #(CLK_PERIOD/2) clk <= ~clk;
  end
  
  // Waveform generation
  initial begin
    $dumpfile("test_aesfsm.vcd");
    $dumpvars(0, test_fsm);
  end
  
  // =========== FSM Test ===========
  logic fsm_load_en, fsm_init_en, fsm_run_en, fsm_nlfsr3_ce;
  
  fsm fsm_inst (
    .clk(clk),
    .rst(rst),
    .load_en(fsm_load_en),
    .init_en(fsm_init_en),
    .run_en(fsm_run_en),
    .nlfsr3_ce(fsm_nlfsr3_ce)
  );
  
  task automatic test_fsm_states();
    begin
      // Test LOAD state
      assert(fsm_load_en == 1'b1 && fsm_init_en == 1'b0 && fsm_run_en == 1'b0) else
        $error("FSM not in correct LOAD state at startup");
      
      // Wait for transition to INIT (after 17 cycles)
      repeat(17) @(posedge clk);
      
      assert(fsm_load_en == 1'b0 && fsm_init_en == 1'b1 && fsm_run_en == 1'b0) else
        $error("FSM did not transition to INIT state after 17 cycles");
      
      // Wait for transition to RUN (after additional 36 cycles)
      repeat(36) @(posedge clk);
      
      assert(fsm_load_en == 1'b0 && fsm_init_en == 1'b0 && fsm_run_en == 1'b1) else
        $error("FSM did not transition to RUN state after 36 more cycles");
      
      // Test nlfsr3_ce signal in RUN state (should be active every 5th cycle)
      @(posedge clk);
      for (int i = 1; i <= 10; i++) begin
        @(posedge clk);
        if (i % 5 == 0) begin
          assert(fsm_nlfsr3_ce == 1'b1) else
            $error("FSM nlfsr3_ce not active on 5th cycle during RUN state");
        end else begin
          assert(fsm_nlfsr3_ce == 1'b0) else
            $error("FSM nlfsr3_ce active on non-5th cycle during RUN state");
        end
      end
    end
  endtask
  
  // Main test sequence
  initial begin
    // Initialize signals
    clk = 0;
    rst = 1;
    
    // Release reset
    #(CLK_PERIOD * 2);
    rst = 0;
    #CLK_PERIOD;
    
    // Test FSM
    $display("Testing FSM module...");
    test_fsm_states();
    
    // Finish simulation
    #(CLK_PERIOD * 10);
    $display("FSM test completed!");
    $finish();
  end

endmodule

tests/test_fsm/test_fsm.vcd
$version Generated by VerilatedVcd $end
$timescale 1ps $end
 $scope module $rootio $end
 $upscope $end
 $scope module test_fsm $end
  $var wire 1 ) clk $end
  $var wire 1 * rst $end
  $var wire 32 + CLK_PERIOD [31:0] $end
  $var wire 1 # fsm_load_en $end
  $var wire 1 $ fsm_init_en $end
  $var wire 1 % fsm_run_en $end
  $var wire 1 & fsm_nlfsr3_ce $end
  $scope module fsm_inst $end
   $var wire 1 ) clk $end
   $var wire 1 * rst $end
   $var wire 1 # load_en $end
   $var wire 1 $ init_en $end
   $var wire 1 % run_en $end
   $var wire 1 & nlfsr3_ce $end
   $var wire 3 , LOAD [2:0] $end
   $var wire 3 - INIT [2:0] $end
   $var wire 3 . RUN [2:0] $end
   $var wire 3 ' state [2:0] $end
   $var wire 6 ( cnt [5:0] $end
  $upscope $end
 $upscope $end
$enddefinitions $end


#0
0#
0$
0%
0&
b000 '
b000000 (
0)
1*
b00000000000000000000000000001010 +
b100 ,
b010 -
b001 .
#5000
1#
1&
b100 '
1)
#10000
0)
#15000
1)
#20000
0)
0*
#25000
b000001 (
1)
#30000
0)
#35000
b000010 (
1)
#40000
0)
#45000
b000011 (
1)
#50000
0)
#55000
b000100 (
1)
#60000
0)
#65000
b000101 (
1)
#70000
0)
#75000
b000110 (
1)
#80000
0)
#85000
b000111 (
1)
#90000
0)
#95000
b001000 (
1)
#100000
0)
#105000
b001001 (
1)
#110000
0)
#115000
b001010 (
1)
#120000
0)
#125000
b001011 (
1)
#130000
0)
#135000
b001100 (
1)
#140000
0)
#145000
b001101 (
1)
#150000
0)
#155000
b001110 (
1)
#160000
0)
#165000
b001111 (
1)
#170000
0)
#175000
b010000 (
1)
#180000
0)
#185000
b010001 (
1)
